{"id":"5ab90589f07aee697709c7a0","_id":"5ab90589f07aee697709c7a0","name":"Running_Tips_1280x720.svg","width":1280,"height":720,"category":"Sport & Extreme","categoryCaption":"sportExtreme","group":"HC","measureUnits":"px","driveFileIds":["1soEbQekTvBobKP9YFuoZlK2DlKyRSlKx"],"template":[{"animationMode":"elements","customAnimationDuration":0,"elements":[{"top":-0.4,"left":-1.6,"width":1281.7,"height":725.6,"angle":0,"uuid":"kqVVZnIxej9HUJYGyrvlNWuOPiWVU43fFZY1KNJsa9IjPOzEvv5Vv9TibsWAypuN","templateAsset":true,"mediaId":"5ab905a8f07aee69770a18b1","opacity":1,"isFreeItem":false,"flipHorizontal":1,"flipVertical":1,"isBackground":false,"type":"imageElement","locked":false,"dphId":"122607588","filters":{"brightness":0,"contrast":0,"saturate":0,"tint":0,"blur":0,"crossProcess":0,"vignette":0},"filtersIntensityEnabled":false,"filtersPresetIntensity":50,"originalImageWidth":1447.9,"originalImageHeight":965.2,"cropOpts":{"left":166.2,"top":53.4,"width":1281.7,"height":725.6},"position":{"left":-1.6,"top":-0.4}},{"top":1.96986301369863,"left":1,"width":1279,"height":719.4,"angle":0,"uuid":"JKsu6ukgbOiSggGMWDoRBlK2uCuE79Tj8f8WPZrg0bu9otUbL6jbyZ9tk1VhhtI3","templateAsset":true,"mediaId":"5ab905a8f07aee69770a1860","opacity":0.65,"isFreeItem":true,"flipHorizontal":1,"flipVertical":1,"isBackground":false,"type":"svgElement","locked":false,"colors":[{"id":0,"color":"#100"}],"position":{"left":1,"top":1.96986301369863}},{"top":219.9,"left":314.5,"width":627,"height":130.9,"angle":0,"uuid":"b2z5Ye59oIbknAJ89mwpKe7cJjWBqKKAJDeXvcfkRVqNgqlDYxBD22XxNPYuKEnx","templateAsset":true,"opacity":1,"isFreeItem":true,"type":"textElement","locked":false,"fontSize":132,"font":"Allerta Stencil","lineHeight":1,"wordBreak":"breakWord","colorMap":[{"startIndex":0,"type":"color","value":"FFFFFF","endIndex":6}],"boldMap":[{"startIndex":0,"type":"bold","value":false,"endIndex":6}],"italicMap":[{"startIndex":0,"type":"italic","value":false,"endIndex":6}],"lineMap":[{"startIndex":0,"endIndex":6}],"textAlign":"right","capitalize":false,"underline":false,"letterSpacing":2,"text":"RUNNING","position":{"left":314.5,"top":219.9}},{"top":386,"left":349,"width":581,"height":90,"angle":0,"uuid":"wRCWwOSSKnPKf4gd3RyQzLkIFFWSzw51rNq4bIo1A27C5O75Gt4k61xzv1nyHGUE","templateAsset":true,"mediaId":"5ab905a8f07aee69770a185f","opacity":1,"isFreeItem":true,"flipHorizontal":1,"flipVertical":1,"isBackground":false,"type":"svgElement","locked":false,"colors":[{"id":0,"color":"#B48C66"}],"position":{"left":349,"top":386}},{"top":394.6,"left":519.9,"width":266,"height":75.3,"angle":0,"uuid":"BbGsnRHESNZ6dCiJilk8qv8OxYQ2ITnU2Q8d3bqgg32p5OZwfdSBDEn8orx3ktwj","templateAsset":true,"opacity":1,"isFreeItem":true,"type":"textElement","locked":false,"fontSize":76,"font":"Alfa Slab One","lineHeight":1,"wordBreak":"breakWord","colorMap":[{"startIndex":0,"type":"color","value":"FFFFFF","endIndex":3}],"boldMap":[{"startIndex":0,"type":"bold","value":false,"endIndex":3}],"italicMap":[{"startIndex":0,"type":"italic","value":false,"endIndex":3}],"lineMap":[],"textAlign":"center","capitalize":false,"underline":false,"letterSpacing":6,"text":"TIPS","position":{"left":519.9,"top":394.6}}],"audio":[],"uuid":"R4F89gfBgUHRHH9JvX6rGiXaZszi5usESaQxWuMCQxLkx5PcPpQMoINbNfVjkbYA"}],"templateType":"regular","hash":"1bO1VNxQSBHHgDOgnaxIGxnCe0Fhx4_WW","pixelWidth":1280,"pixelHeight":720,"previewImageUrls":["/downloads/58c2f405-d0ea-4470-a530-ad5c9a1d09b3.jpeg"],"hasAnimatedPreview":false,"hasAnimatedScreenPreview":false,"downloadUrl":"https://drive.google.com/uc?id=1soEbQekTvBobKP9YFuoZlK2DlKyRSlKx&export=download","status":"completed","format":"Youtube Thumbnail","suitability":["mobile"],"folder":"https://drive.google.com/drive/folders/1bO1VNxQSBHHgDOgnaxIGxnCe0Fhx4_WW","errors":[],"warnings":[{"msg":"TextElement contain disallowed font-family. Detected font-family: Allerta_Stencil","type":"warning","level":5,"code":"fontOutOfWhiteList","systemId":"f780db28-b9b4-44ec-a0db-640e93be16ad","details":{"fontFamily":"Allerta_Stencil"}},{"msg":"TextElement contain disallowed font-family. Detected font-family: Alfa_Slab_One","type":"warning","level":5,"code":"fontOutOfWhiteList","systemId":"95d80868-cd68-44a0-8c50-8bed0333cdc7","details":{"fontFamily":"Alfa_Slab_One"}}],"studioName":"iStar","createdAt":1522075017555,"updatedAt":1612362159845,"acceptedAt":1565429802852,"attributedAt":1588955099010,"keywords":{"en":["action","activity","athlete","cardio","endurance","fitness","health","marathon","motivation","race","runner","self improvement","sport","woman","running","training","workout","urban","city","youtube","thumbnail"],"ru":["экшен","активности","атлет","кардио","выносливость","фитнес","здоровье","марафон","мотивация","гонка","бегун","самосовершенствование","спорт","женщина","бежит","тренироваться","тренировка","городские","город"],"uk":["екшен","активність","атлет","кардіо","витривалість","фітнес","здоров’я","марафон","мотивація","гонка","бігун","самовдосконалення","спорт","жінка","біжить","тренування","тренування","міський","місто"],"es":["acion","actividad","atleta","cardio","resistencia","musculación","la salud","maratón","motivaciin","carreraa","carredor","la superación personal","deporte es","mujer e","ejecutándose","entrensmiento","rutina de ejercicio","urbanos","coiudad"],"pt":["açãi","actividade","atleta","cardio","resistência","ginástica","tele saude","maratona","motivalção","corrida","corridedor","auto-aperfeiçoamento","outro sport","mulher a olhar","atropelamento","teinamentos","malhaçao","urbano","cidade g"],"nl":["in actie","delden activiteit","atleet","cardio","uithoudingsvermogen","fitheid","gezondhied","marathonloop","motivatie","racen","hardloopster","zelfverbetering","sport","een vrouw","lopend","bijscholing","training","stedelijk","de stad"],"fr":["passer a l'action","activite","athléte","cardio","endurance","fitness ou","bien être santé","la marathon","motivation","course","coureur à pied","l'amélioration personnelle","le sport d","efemé","course a pieds","auto formation","faire des exercices","urbain","cité"],"de":["vorgehen","aktivität","athlet","cardio","ausdauer","fitness","geseundheit","marathon-","motivation","rennen","läufer","selbstverbesserung","rücken sport","woman das","laufsport","zu viel training","trainieren","städtisch","stadt f"],"it":["in azione","attività","atleta","cardio","resistenza","forma fisica","sanitarie","maratona","motivazione","gara","corridore","auto-miglioramento","sport","donna di spalle","in esecuzione","corso di formazione","allenarsi","urbani","citta"],"pl":["akcja","aktywność","silacz","cardio","wytrzymałość","fitness mam","zdrowie","maraton","motywacja","wyścig","biegacz","doskonalenie siebie","sport","stara kobieta","po bieganiu","tresura","trening","miejski","miasto"],"tr":["aksiyon","aktivite","atlet","kardiyo","dayanıklılık","fitness","sağlik","maraton","motivasyon","yariş","koşucu","öz gelişim","spor","kadın","koşu","eğitim","egzersiz yapmak","kentsel","şehir"],"ja":["アクション","アクティビティ","アスリート","心肺機能","耐久","フィットネス","健康","マラソン","動機","人種","ランナー","自己改善","スポーツ","女性","ランニング","トレーニング","いい結果になる","都市","市"],"cs":["akci","posilovna","zdraví","školení"]},"industries":["educationTraining","healthWellness","sportFitness"],"languages":["en"],"title":"Running Tips Woman Running in City","localizedTitle":{"en":"Running Tips Woman Running in City","ru":"Запуск Советы Женщина работает в городе","uk":"Поради щодо роботи жінка працює в місті","es":"Consejos para correr Mujer corriendo en la ciudad","pt":"Dicas de corrida Mulher correndo na cidade","nl":"Running Tips Vrouw loopt in de stad","fr":"Conseils de course Femme qui court en ville","de":"Lauftipps Frau, die in der Stadt läuft","it":"Consigli per la corsa Donna che corre in città","pl":"Porady dotyczące biegania Kobieta w mieście","tr":"Çalışan ipuçları şehirde çalışan kadın","ja":"ランニングのヒント街で走っている女性","cs":"Tipy pro běh žena ve městě"},"forSubscribers":false,"v2":true,"language":"en","seoMeta":{"shouldIndex":true}}