{"id":"5d68eface79a2a634ec6f748","_id":"5d68eface79a2a634ec6f748","name":"03_Profitable.svg","width":1280,"height":720,"category":"Business & Finance","categoryCaption":"businessFinance","group":"HC","measureUnits":"px","driveFileIds":["18g4fuMR6KknEdu8yEFdTFq7uUQyGis5U"],"template":[{"elements":[{"uuid":"9vstWqIBIbMy0e1PJ3LqKKa3sZQEyjZIxbrLtV71eyaFoR3l9c4NSvV3ExpSpB7u","width":578,"height":720,"angle":0,"originalAngle":0,"id":"5d68efb4e79a2a634ec7077f","innerId":0,"type":"svgElement","templateAsset":true,"position":{"left":0,"top":0},"opacity":1,"mediaAsset":true,"mediaId":"5d68efb4e79a2a634ec707fb","isFreeItem":true,"flipped":{"horizontal":1,"vertical":1},"isBackground2":false,"hasBackgroundLabel":true,"colors":[{"id":0,"color":"#1D2C4E"}],"newColors":[null],"special":true,"renderMode":true,"isSharedProject":true},{"uuid":"SpRaBas74vI72pclm1a0Dy796DpJgAplvxype211mTK7WRS3OkuMtwrCvwodrRPF","width":838,"height":720,"angle":0,"originalAngle":0,"id":"5d68efb5e79a2a634ec70ad7","innerId":1,"type":"svgElement","templateAsset":true,"position":{"left":442,"top":0},"opacity":1,"mediaAsset":true,"mediaId":"5d68efb5e79a2a634ec70b07","isFreeItem":true,"flipped":{"horizontal":1,"vertical":1},"isBackground2":false,"hasBackgroundLabel":true,"colors":[{"id":0,"color":"#F5A047"}],"newColors":[null],"special":true,"renderMode":true,"isSharedProject":true},{"uuid":"Zk9Z8xyjx1KeLFfrucSKLuAqClPdnTOF6o1Fm4U65O0I0aOBPOZkm1AdrkN4ZET4","width":1055.6,"height":651.8,"angle":0,"originalAngle":0,"id":"5d68efb2e79a2a634ec703d3","innerId":2,"type":"maskElement","templateAsset":true,"position":{"left":37.1,"top":34.5},"opacity":1,"mediaAsset":true,"mediaId":"5d68efb2e79a2a634ec70400","dphId":"183375892","isFreeItem":false,"flipped":{"horizontal":1,"vertical":1,"undefined":-1},"hasBackgroundLabel":true,"stickedImageData":{"id":"5d68efb2e79a2a634ec702f3","mediaAsset":true,"mediaId":"5d68efb2e79a2a634ec702ff"},"imagePosition":{"x":20.815542163008104,"y":-29.620509561410017,"width":1080.6730488257394,"height":721.01159470487},"presetPic":false,"filters":{"brightness":0,"contrast":0,"saturate":0,"tint":0,"blur":0,"crossProcess":0,"vignette":0},"filtersPreset":false,"filtersPresetIntensity":50,"filtersIntensityEnabled":false,"filtersStyle":{"overflow":"hidden","filter":"","background":"linear-gradient(rgba(0, 255, 255, 0.15), rgba(0, 255, 255, 0.15))"},"colors":[{"id":0,"color":"none"}],"cropping":false,"renderMode":true,"isSharedProject":true},{"uuid":"THTB2MA2Tbe7pMkIEecFYNYFinmiF42WUGYHque3fHrMq7bOqjW2Hq6zu1PHWEaB","width":676,"height":416,"angle":0,"originalAngle":0,"id":"5d68efb5e79a2a634ec70a91","innerId":3,"type":"svgElement","templateAsset":true,"position":{"left":578,"top":227},"opacity":1,"mediaAsset":true,"mediaId":"5d68efb5e79a2a634ec70ab2","isFreeItem":true,"flipped":{"horizontal":1,"vertical":1},"isBackground2":false,"hasBackgroundLabel":true,"colors":[{"id":0,"color":"#1C2133"}],"newColors":[null],"special":false,"renderMode":true,"isSharedProject":true},{"uuid":"fTDhTqcXKm1YaHMKC6MCZleG13BY3WbQQ0SL7cKXHdDbwc5wa6ob0kAsc6SsoZlO","width":226,"height":368,"angle":0,"originalAngle":0,"id":"5d68efb5e79a2a634ec70aa6","innerId":4,"type":"svgElement","templateAsset":true,"position":{"left":906,"top":192},"opacity":1,"mediaAsset":true,"mediaId":"5d68efb5e79a2a634ec70ad2","isFreeItem":true,"flipped":{"horizontal":1,"vertical":1},"isBackground2":false,"hasBackgroundLabel":true,"colors":[{"id":0,"color":"#1D2C4E"}],"newColors":[null],"special":false,"renderMode":true,"isSharedProject":true},{"uuid":"WyOUgpc0ReLzP6VqH280XRkLiWMFGrYIEEAwLQzQFhzP33BoWjkB3M5Z3jkWelFA","width":159,"height":131,"angle":0,"originalAngle":0,"id":"5d68efb5e79a2a634ec70b4b","innerId":5,"type":"svgElement","templateAsset":true,"position":{"left":0,"top":342},"opacity":1,"mediaAsset":true,"mediaId":"5d68efb5e79a2a634ec70b62","isFreeItem":true,"flipped":{"horizontal":1,"vertical":1},"isBackground2":false,"hasBackgroundLabel":true,"colors":[{"id":0,"color":"#F5A047"}],"newColors":[null],"special":false,"renderMode":true,"isSharedProject":true},{"uuid":"W1IAUboCiHrc9zZroHgydgsNQcjkdLqs1mEjEl8xPsrk4MzBqd5lR7dFtU3y3MyV","width":159,"height":131,"angle":0,"originalAngle":0,"id":"5d68efb4e79a2a634ec70960","innerId":6,"type":"svgElement","templateAsset":true,"position":{"left":1089.7,"top":33.7},"opacity":1,"mediaAsset":true,"mediaId":"5d68efb5e79a2a634ec709d3","isFreeItem":true,"flipped":{"horizontal":1,"vertical":1},"isBackground2":false,"hasBackgroundLabel":true,"colors":[{"id":0,"color":"#1C2133"}],"newColors":[null],"special":false,"renderMode":true,"isSharedProject":true},{"uuid":"V5yAJwFCF3lGh3vSYyd28fNNJqP9Ofz0GUYQMgxXT43DPqLSjDMywBVpPCcpW396","width":159,"height":131,"angle":0,"originalAngle":0,"id":"5d68efb5e79a2a634ec70afc","innerId":7,"type":"svgElement","templateAsset":true,"position":{"left":553,"top":590},"opacity":1,"mediaAsset":true,"mediaId":"5d68efb5e79a2a634ec70b35","isFreeItem":true,"flipped":{"horizontal":1,"vertical":1},"isBackground2":false,"hasBackgroundLabel":true,"colors":[{"id":0,"color":"#1D2C4E"}],"newColors":[null],"special":false,"renderMode":true,"isSharedProject":true},{"uuid":"URBNzi5MjrXW9Ro7UuSt3SwOsWkS8K5LNodP5n74yq87z9q5gwWKCS2vPc1drj4d","width":610.7,"height":196,"angle":0,"originalAngle":0,"id":9,"innerId":8,"type":"textElement","templateAsset":true,"position":{"left":639.9943527398231,"top":280.13127413127415},"opacity":1,"mediaAsset":false,"isFreeItem":true,"hasBackgroundLabel":true,"text":"PROFITABLE BUSINESS IDEAS","fontSize":83.0908462453576,"font":"Oswald","lineHeight":1.19,"wordBreak":"breakWord","colorMap":[{"startIndex":0,"type":"color","value":"F5A047","endIndex":24}],"boldMap":[{"startIndex":0,"type":"bold","value":true,"endIndex":24}],"italicMap":[{"startIndex":0,"type":"italic","value":false,"endIndex":24}],"textAlign":"left","lineMap":[{"startIndex":0,"endIndex":10},{"startIndex":11,"endIndex":24}],"capitalize":false,"underline":false,"letterSpacing":0.9921921986785741,"__disableUnlockSelection":false,"renderMode":true,"isSharedProject":true},{"uuid":"Qk7tZkPJaZ4T6BLPHaQBNZ54RDr8hoUoz8tK3klIlmqqJkvoMXs9lAuEZ0Joheqs","width":345,"height":47,"angle":0,"originalAngle":0,"id":10,"innerId":9,"type":"textElement","templateAsset":true,"position":{"left":874,"top":530},"opacity":1,"mediaAsset":false,"isFreeItem":true,"hasBackgroundLabel":true,"text":"BY SELBY DORCAS","fontSize":47,"font":"Oswald","lineHeight":1,"wordBreak":"breakAll","colorMap":[{"startIndex":0,"type":"color","value":"FFFFFF","endIndex":14}],"boldMap":[{"startIndex":0,"type":"bold","value":false,"endIndex":14}],"italicMap":[{"startIndex":0,"type":"italic","value":false,"endIndex":14}],"textAlign":"left","lineMap":[],"capitalize":false,"underline":false,"letterSpacing":0,"renderMode":true,"isSharedProject":true}],"pageNumber":0}],"templateType":"regular","hash":"1MLxpLsWor6WrhQ6iMqpalLB893oGcHlV","pixelWidth":1280,"pixelHeight":720,"previewImageUrls":["/common/40150310-55c8-4af7-b9a9-07e9012f7b36.jpg"],"hasAnimatedPreview":false,"hasAnimatedScreenPreview":false,"downloadUrl":"https://drive.google.com/uc?id=18g4fuMR6KknEdu8yEFdTFq7uUQyGis5U&export=download","status":"completed","format":"Youtube Thumbnail","suitability":["mobile"],"folder":"https://drive.google.com/drive/folders/1MLxpLsWor6WrhQ6iMqpalLB893oGcHlV","studioName":"iStar","createdAt":1567158188723,"updatedAt":1589450101759,"acceptedAt":1570731451369,"attributedAt":1588959416771,"keywords":{"en":["blog","browsing","business","man","computer","creativity","device","digital","freelance","freelancer","internet","laptop","media","network","online","remote work","social media","web","website","wireless","working","workplace","stairs","african american","black people","youtube","thumbnail"],"ru":["блог","просмотр","бизнес","мужчина","компьютер","творчество","устройство","цифровой","фриланс","свободный художник","интернет","ноутбук","медиа","сеть","онлайн","удаленная робота","социальные медиа","веб","вебсайт","беспроводной","работает","рабочее место","лестница","афроамериканець"],"uk":["блог","перегляд","бізнес","чоловік","комп’ютер","творчість","пристрій","цифровий","позаштатно","фрілансер","інтернет","ноутбук","медіа","мережа","онлайн","віддалена робота","соціальні медіа","веб","вебсайт","бездротові","працює","робче місце","сходинки","афроамериканця"],"es":["blog en","navegando","nombre de negocio","ancianito","encendido apagado computadora","cratividad","dispositivo de","dşgital","lanza libre","persona de libre dedicación","de internet","con portatil","medios de comunicacion antiguos","red de","todos en linea","trabajo a distancia","social medía","web tenemos","tu pagina web","inalambrico","seguimos trabajando","plaza de trabajo","escaleras desde arriba","afroamericano"],"pt":["blogue","navegação","negócias","homem idoso","olhando computador","criacia","dispositivo","digital ex","freelance","trabalhador autônomo","curso internet","computador portátil","mídias y","rede","curso on line","trabalho remoto","mídia sociais","teia","website deve","sem fio","trabalhandpo","ambiente de trabalho","subindo escadas","afro-americano"],"nl":["blog","browsing","zakelij","van man","computer en","creativiteit","apparaat","digitaal","freelance","freelancer","internet","laptop s","media gebruik","netwerk","cursus online","afstandswerk","sociaalmedia","web","nieuw website","draadloze","werkend","werkplek","trappetje","afrikaanse amerikaan"],"fr":["bloguer","navigation","nouveau commerce","meme man","ordianateur","créativity","dispositif","numã©riques","free-lance","travailleur indépendant","internet droit","laptop des","médiathèque","network et","cours en ligne","travail a distance","mã©dia sociaux","web droit","nouveau site web","sans fil","travail","poste de travail","escaliers","afro-américain"],"de":["blog","surfen","geschã¤ftlich","mann hilfe","edv kurs","kreativität","gerät","digital","freiberuflich","freiberufler","i̇nternet","laptop","medien","hnetzwerk","online war","heimarbeit","sozialmedien","netz","webeite","kabellos","arbeiten","arbeitsplatz","treppen","afroamerikaner"],"it":["blog","navigazione","business prese","uom","corso computer","creatività","dispositivo","digitali","libero professionista","libero professionista","internet i con","il computer portatile","l media","rete","corso on line","lavoro a distanza","sociale  media","web dei","sito we","senza fili","lavora","posto di lavoro","le scale","afroamericano"],"pl":["blog","przeglądanie","twój biznes","czlowiek myslec","w komputerze","kreatywność","urzä…dzenie","cyfrowy","wolny zawód","wolny strzelec","internetowe","z laptopem","głoska bezdźwięczna","sieć","online","praca zdalna","socjal media","sieć","strona www","bezprzewodowy","pracy","miejsce pracy","schody","afroamerykanin"],"tr":["blog","tarama","e iş","erkek sa","bilgisayar","yaratıcılık","cihaz","dijital","serbest","bağımsız yazar","internet","dizüstü","medya","ağ","online biz","uzaktan çalışma","sosyal mesya","ağ","web sitesi","kablosuz","çalışma","i̇ş yeri̇","merdivenler","afrikan amerikan"],"ja":["ブログ","ブラウジング","ビジネス","おとこ","コンピューター","創造性","端末","デジタル","フリーランス","フリーランサー","インターネット","ラップトップ","メディア","通信網","オンライン","リモートワーク","ソーシャルメディア","ウェブ","ウェブサイト","無線","ワーキング","職場","階段","アフリカ系アメリカ人"],"cs":["podnikání","počitač"]},"industries":["businessFinance","corporate","educationTraining","techGadgets"],"languages":["en"],"title":"Business Courses Ad Man Working on Laptop","localizedTitle":{"en":"Business Courses Ad Man Working on Laptop","ru":"Бизнес курсы Ad Man работает на ноутбуке","uk":"Бізнес-курси Ad Man працює на ноутбуці","es":"Cursos de negocios Ad Man Working on Laptop","pt":"Homem de anúncio de cursos de negócios trabalhando no laptop","nl":"Bedrijfscursussen Ad Man die op laptop werkt","fr":"Cours d'affaires Ad Man travaillant sur ordinateur portable","de":"Business Courses Ad Man Arbeiten am Laptop","it":"Uomo di annuncio di corsi di affari che lavora al computer portatile","pl":"Biznes Kursy Ad Man działa na laptopie","tr":"İş kursları dizüstü bilgisayarda çalışan adam","ja":"ラップトップに取り組んでビジネスコースの広告男","cs":"Obchodní kurzy Ad Man pracuje na notebooku"},"forSubscribers":true,"language":"en","seoMeta":{"shouldIndex":true}}