{"id":"5d68ef8ce79a2a634ec6b63d","_id":"5d68ef8ce79a2a634ec6b63d","name":"02_Start.svg","width":1280,"height":720,"category":"Business & Finance","categoryCaption":"businessFinance","group":"HC","measureUnits":"px","driveFileIds":["1VRJc1BM2651YMxTvir1eQSOOvDgBH-C-"],"template":[{"elements":[{"uuid":"W5ZbXf8DJsKr1ZJhkPkyCuWIrlZ9bzcWvS635WhycD4R4okYxHiyipOe7IKsauyP","width":1788.5,"height":1193.7,"angle":0,"originalAngle":0,"id":"5d68ef96e79a2a634ec6c91b","innerId":0,"type":"imageElement","templateAsset":true,"position":{"left":-340,"top":-14.7},"opacity":1,"mediaAsset":true,"mediaId":"5d68ef96e79a2a634ec6c9a7","dphId":"153068556","isFreeItem":false,"flipped":{"horizontal":1,"vertical":1},"isBackground2":true,"hasBackgroundLabel":true,"filters":{"brightness":0,"contrast":0,"saturate":0,"tint":0,"blur":0,"crossProcess":0,"vignette":0},"filtersPreset":false,"filtersPresetIntensity":50,"filtersIntensityEnabled":false,"originalImageWidth":1788.5,"originalImageHeight":1193.7,"cropOpts":{"left":0,"top":0,"width":0,"height":0},"sticky":true,"renderMode":true,"isSharedProject":true},{"uuid":"zq1Hdr7LqzB2qeNrLiCTDqDmIIYyWsDhZLECzCAtxt77g90hKWYI7kARgEojtB4n","width":116,"height":30,"angle":0,"originalAngle":0,"id":"5d68ef98e79a2a634ec6cd42","innerId":1,"type":"svgElement","templateAsset":true,"position":{"left":1123,"top":45},"opacity":1,"mediaAsset":true,"mediaId":"5d68ef98e79a2a634ec6cdcd","isFreeItem":true,"flipped":{"horizontal":1,"vertical":1},"isBackground2":false,"hasBackgroundLabel":true,"colors":[{"id":0,"color":"#02AB9E"}],"newColors":[null],"special":true,"renderMode":true,"isSharedProject":true},{"uuid":"7uDv3ZEkvxWKz7dLbZAZJVFPR0Gxm8nA0HIA7Tbq3tCW1sdK3DPn3Po95puZbGos","width":657,"height":30,"angle":0,"originalAngle":0,"id":"5d68ef98e79a2a634ec6ce64","innerId":2,"type":"svgElement","templateAsset":true,"position":{"left":582,"top":393},"opacity":1,"mediaAsset":true,"mediaId":"5d68ef98e79a2a634ec6ced6","isFreeItem":true,"flipped":{"horizontal":1,"vertical":1},"isBackground2":false,"hasBackgroundLabel":true,"colors":[{"id":0,"color":"#02AB9E"}],"newColors":[null],"special":true,"renderMode":true,"isSharedProject":true},{"uuid":"kKw4FB6Z23Mym1skDVNt1EygIWqABz1mE4NOBRPIlQHRrsrc4lZrmRvAMvQMv7s8","width":657,"height":30,"angle":0,"originalAngle":0,"id":"5d68ef98e79a2a634ec6ce5a","innerId":3,"type":"svgElement","templateAsset":true,"position":{"left":582,"top":288},"opacity":1,"mediaAsset":true,"mediaId":"5d68ef98e79a2a634ec6cec8","isFreeItem":true,"flipped":{"horizontal":1,"vertical":1},"isBackground2":false,"hasBackgroundLabel":true,"colors":[{"id":0,"color":"#02AB9E"}],"newColors":[null],"special":true,"renderMode":true,"isSharedProject":true},{"uuid":"Ml6pbJbXQdUisxfvyJzQa1ggVLBySeKceXTXTSa661kAh5WdpJ43aerrbk6lYaUE","width":621,"height":667,"angle":0,"originalAngle":0,"id":"5d68ef99e79a2a634ec6d09b","innerId":4,"type":"svgElement","templateAsset":true,"position":{"left":599,"top":0},"opacity":0.75,"mediaAsset":true,"mediaId":"5d68ef99e79a2a634ec6d0ad","isFreeItem":true,"flipped":{"horizontal":1,"vertical":1},"isBackground2":false,"hasBackgroundLabel":true,"colors":[{"id":0,"color":"#13100D"}],"newColors":[null],"special":true,"renderMode":true,"isSharedProject":true},{"uuid":"qLGzgqXCP9jgxw1F2oKJJR9KYFCCobP1xVNv9qsf531lUY7MB0cwutF3tJufhSQr","width":253,"height":75,"angle":0,"originalAngle":0,"id":"5d68ef99e79a2a634ec6cfdf","innerId":5,"type":"svgElement","templateAsset":true,"position":{"left":777.9,"top":116},"opacity":1,"mediaAsset":true,"mediaId":"5d68ef99e79a2a634ec6d026","isFreeItem":true,"flipped":{"horizontal":1,"vertical":1},"isBackground2":false,"hasBackgroundLabel":true,"colors":[{"id":0,"color":"#02AB9E"}],"newColors":[null],"special":true,"renderMode":true,"isSharedProject":true},{"uuid":"ynPW2gtq0N6aQ7lHH2xntf5EVYN8k0TcOANW00iCd2d8uwqO9dO82qU9duutqoYN","width":274.5,"height":37,"angle":0,"originalAngle":0,"id":7,"innerId":6,"type":"textElement","templateAsset":true,"position":{"left":771.0872161029569,"top":136.91781959048146},"opacity":1,"mediaAsset":false,"isFreeItem":true,"hasBackgroundLabel":true,"text":"HOW TO","fontSize":37.61181066185313,"font":"Nunito","lineHeight":1,"wordBreak":"breakWord","colorMap":[{"startIndex":0,"type":"color","value":"000001","endIndex":5}],"boldMap":[{"startIndex":0,"type":"bold","value":true,"endIndex":5}],"italicMap":[{"startIndex":0,"type":"italic","value":false,"endIndex":5}],"textAlign":"center","lineMap":[{"startIndex":0,"endIndex":5}],"capitalize":false,"underline":false,"letterSpacing":9.148818809639948,"__disableUnlockSelection":false,"renderMode":true,"isSharedProject":true},{"uuid":"8aXLvICNb4BkozrOjEpghCRbrfMWwUwHtrtme5KpUgJofmdVcwth1WcBFl9HZxre","width":355.3,"height":45,"angle":0,"originalAngle":0,"id":8,"innerId":7,"type":"textElement","templateAsset":true,"position":{"left":722.252251190832,"top":562.7629305690531},"opacity":1,"mediaAsset":false,"isFreeItem":true,"hasBackgroundLabel":true,"text":"Galilee Vonne","fontSize":45.84865152085454,"font":"Nunito","lineHeight":1,"wordBreak":"breakWord","colorMap":[{"startIndex":0,"type":"color","value":"FFFFFF","endIndex":12}],"boldMap":[{"startIndex":0,"type":"bold","value":true,"endIndex":12}],"italicMap":[{"startIndex":0,"type":"italic","value":false,"endIndex":12}],"textAlign":"center","lineMap":[{"startIndex":0,"endIndex":12}],"capitalize":false,"underline":false,"letterSpacing":0,"__disableUnlockSelection":false,"renderMode":true,"isSharedProject":true},{"uuid":"NB6tTFFxZAlinngdYjgyya8iWU1nJuFvNENXUloam8dC0IpuOPuIkors7MsibcXH","width":272.4,"height":19,"angle":0,"originalAngle":0,"id":9,"innerId":8,"type":"textElement","templateAsset":true,"position":{"left":763.7065397683873,"top":533.4608033689667},"opacity":1,"mediaAsset":false,"isFreeItem":true,"hasBackgroundLabel":true,"text":"Business analyst","fontSize":19.45599418768363,"font":"Nunito","lineHeight":1,"wordBreak":"breakWord","colorMap":[{"startIndex":0,"type":"color","value":"02AB9E","endIndex":15}],"boldMap":[{"startIndex":0,"type":"bold","value":true,"endIndex":15}],"italicMap":[{"startIndex":0,"type":"italic","value":false,"endIndex":15}],"textAlign":"center","lineMap":[{"startIndex":0,"endIndex":15}],"capitalize":false,"underline":false,"letterSpacing":4.863998546920907,"__disableUnlockSelection":false,"renderMode":true,"isSharedProject":true},{"uuid":"zhCQlsquMRisFZDuniyhJPCPvtyHzF9529rWvq3CQ1SwsLQbXEwevldBGP023EpT","width":640,"height":200,"angle":0,"originalAngle":0,"id":10,"innerId":9,"type":"textElement","templateAsset":true,"position":{"left":591.8317653569453,"top":252.65818114738974},"opacity":1,"mediaAsset":false,"isFreeItem":true,"hasBackgroundLabel":true,"text":"START A\nBUSINESS","fontSize":107,"font":"Nunito","lineHeight":0.93,"wordBreak":"breakWord","colorMap":[{"startIndex":0,"type":"color","value":"FFFFFF","endIndex":15}],"boldMap":[{"startIndex":0,"type":"bold","value":true,"endIndex":15}],"italicMap":[{"startIndex":0,"type":"italic","value":false,"endIndex":15}],"textAlign":"center","lineMap":[{"startIndex":0,"endIndex":6},{"startIndex":7,"endIndex":15}],"capitalize":false,"underline":false,"letterSpacing":0,"__disableUnlockSelection":false,"renderMode":true,"isSharedProject":true},{"uuid":"ekuQDrkE8W8FGJJ6Qv5Zx95xpa0nhlgzVt0PXlhZvZl0hcz27M5ZkfaptOGXl6R3","width":98,"height":2,"angle":0,"originalAngle":0,"id":"5d68ef99e79a2a634ec6cf9e","innerId":10,"type":"svgElement","templateAsset":true,"position":{"left":861,"top":488},"opacity":1,"mediaAsset":true,"mediaId":"5d68ef99e79a2a634ec6cfdc","isFreeItem":true,"flipped":{"horizontal":1,"vertical":1},"isBackground2":false,"hasBackgroundLabel":true,"colors":[{"id":0,"color":"#02AB9E"}],"newColors":[null],"special":true,"renderMode":true,"isSharedProject":true},{"uuid":"vNPnLUfzU4PcGRZxFLZlNrnerpm3iZlsj50rDCgV92WQEiOMm2IS02cKR46Am9MC","width":116,"height":30,"angle":0,"originalAngle":0,"id":"5d68ef99e79a2a634ec6cf6b","innerId":11,"type":"svgElement","templateAsset":true,"position":{"left":1164,"top":288},"opacity":1,"mediaAsset":true,"mediaId":"5d68ef99e79a2a634ec6cfac","isFreeItem":true,"flipped":{"horizontal":1,"vertical":1},"isBackground2":false,"hasBackgroundLabel":true,"colors":[{"id":0,"color":"#02AB9E"}],"newColors":[null],"special":true,"renderMode":true,"isSharedProject":true},{"uuid":"hFqfKO9GWVtoiTlQGareEZyabr2o0uIAY7TxvNP17xFjeBUijBMPiwehTRCb8hK7","width":116,"height":30,"angle":0,"originalAngle":0,"id":"5d68ef97e79a2a634ec6cb67","innerId":12,"type":"svgElement","templateAsset":true,"position":{"left":0,"top":288},"opacity":1,"mediaAsset":true,"mediaId":"5d68ef97e79a2a634ec6cbab","isFreeItem":true,"flipped":{"horizontal":1,"vertical":1},"isBackground2":false,"hasBackgroundLabel":true,"colors":[{"id":0,"color":"#02AB9E"}],"newColors":[null],"special":true,"renderMode":true,"isSharedProject":true},{"uuid":"YrFvBcynvtfEbHuDYUnPD9NNzofH0SHS2DDOZhQ66OfWfuWLsKeRMLeuiY07CSCs","width":116,"height":30,"angle":0,"originalAngle":0,"id":"5d68ef97e79a2a634ec6cc19","innerId":13,"type":"svgElement","templateAsset":true,"position":{"left":582,"top":481},"opacity":1,"mediaAsset":true,"mediaId":"5d68ef97e79a2a634ec6cc4e","isFreeItem":true,"flipped":{"horizontal":1,"vertical":1},"isBackground2":false,"hasBackgroundLabel":true,"colors":[{"id":0,"color":"#02AB9E"}],"newColors":[null],"special":true,"renderMode":true,"isSharedProject":true},{"uuid":"leJeXSACC80X1h6DcwQ9agg7q5Jfb4nlLD2caI7LO2KzmCku92yxFTc2V36Aw2ZX","width":116,"height":30,"angle":0,"originalAngle":0,"id":"5d68ef97e79a2a634ec6cb35","innerId":14,"type":"svgElement","templateAsset":true,"position":{"left":582,"top":45},"opacity":1,"mediaAsset":true,"mediaId":"5d68ef97e79a2a634ec6cb93","isFreeItem":true,"flipped":{"horizontal":1,"vertical":1},"isBackground2":false,"hasBackgroundLabel":true,"colors":[{"id":0,"color":"#02AB9E"}],"newColors":[null],"special":true,"renderMode":true,"isSharedProject":true},{"uuid":"DfEBBuq53yDkCmVVfRml55bn5AYrSvKt0FWF5kTrQsW5YfaVWxVWwCmTi7eEns93","width":116,"height":30,"angle":0,"originalAngle":0,"id":"5d68ef97e79a2a634ec6cbd9","innerId":15,"type":"svgElement","templateAsset":true,"position":{"left":1123,"top":643},"opacity":1,"mediaAsset":true,"mediaId":"5d68ef97e79a2a634ec6cbf3","isFreeItem":true,"flipped":{"horizontal":1,"vertical":1},"isBackground2":false,"hasBackgroundLabel":true,"colors":[{"id":0,"color":"#02AB9E"}],"newColors":[null],"special":true,"renderMode":true,"isSharedProject":true},{"uuid":"EZs37ESu9gcBbzbpAVvoKjeYF6nV2tzy1bLOoRM1HxZ4fqZqxr2xDvGApeaAAGmt","width":41,"height":30,"angle":0,"originalAngle":0,"id":"5d68ef99e79a2a634ec6d008","innerId":16,"type":"svgElement","templateAsset":true,"position":{"left":1123,"top":521},"opacity":1,"mediaAsset":true,"mediaId":"5d68ef99e79a2a634ec6d034","isFreeItem":true,"flipped":{"horizontal":1,"vertical":1},"isBackground2":false,"hasBackgroundLabel":true,"colors":[{"id":0,"color":"#02AB9E"}],"newColors":[null],"special":true,"renderMode":true,"isSharedProject":true},{"uuid":"iccnUuj9AMffqT8gm6qTzI2rGJf5P17Aiy7xfxoeDKffjA4jQxFYI7j2ra2p954b","width":41,"height":30,"angle":0,"originalAngle":0,"id":"5d68ef98e79a2a634ec6cd0a","innerId":17,"type":"svgElement","templateAsset":true,"position":{"left":476,"top":521},"opacity":1,"mediaAsset":true,"mediaId":"5d68ef98e79a2a634ec6ce4a","isFreeItem":true,"flipped":{"horizontal":1,"vertical":1},"isBackground2":false,"hasBackgroundLabel":true,"colors":[{"id":0,"color":"#02AB9E"}],"newColors":[null],"special":true,"renderMode":true,"isSharedProject":true},{"uuid":"N78OIs0l89ewjXRbpPEBmhPNgTDp117hqUbHeklj4SYBK8GSfjsJCVjTg1521qXU","width":41,"height":30,"angle":0,"originalAngle":0,"id":"5d68ef99e79a2a634ec6d001","innerId":18,"type":"svgElement","templateAsset":true,"position":{"left":635,"top":551},"opacity":1,"mediaAsset":true,"mediaId":"5d68ef99e79a2a634ec6d04c","isFreeItem":true,"flipped":{"horizontal":1,"vertical":1},"isBackground2":false,"hasBackgroundLabel":true,"colors":[{"id":0,"color":"#02AB9E"}],"newColors":[null],"special":true,"renderMode":true,"isSharedProject":true},{"uuid":"jv0lEGYoAaFPLePyIjxjvXM3GtIbA6qHx7Xek8APEn9BhYqxnBo1Xl1KS8QdDVWl","width":41,"height":30,"angle":0,"originalAngle":0,"id":"5d68ef98e79a2a634ec6cdd1","innerId":19,"type":"svgElement","templateAsset":true,"position":{"left":38,"top":217},"opacity":1,"mediaAsset":true,"mediaId":"5d68ef98e79a2a634ec6ceb3","isFreeItem":true,"flipped":{"horizontal":1,"vertical":1},"isBackground2":false,"hasBackgroundLabel":true,"colors":[{"id":0,"color":"#02AB9E"}],"newColors":[null],"special":true,"renderMode":true,"isSharedProject":true},{"uuid":"h4FNZwlwGXgVrCwjU8cl1fCr14dlM6h9KEEUYmJzvbSPfm4XVCZiBWYlyh9AIzPV","width":41,"height":30,"angle":0,"originalAngle":0,"id":"5d68ef99e79a2a634ec6d059","innerId":20,"type":"svgElement","templateAsset":true,"position":{"left":38,"top":86},"opacity":1,"mediaAsset":true,"mediaId":"5d68ef99e79a2a634ec6d075","isFreeItem":true,"flipped":{"horizontal":1,"vertical":1},"isBackground2":false,"hasBackgroundLabel":true,"colors":[{"id":0,"color":"#02AB9E"}],"newColors":[null],"special":true,"renderMode":true,"isSharedProject":true}],"pageNumber":0}],"templateType":"regular","hash":"1nFMnnIC1hXe61KiFQebMaTxfhxpWbY53","pixelWidth":1280,"pixelHeight":720,"previewImageUrls":["/common/ec9b2c31-a635-485f-8787-342b88713cdb.jpg"],"hasAnimatedPreview":false,"hasAnimatedScreenPreview":false,"downloadUrl":"https://drive.google.com/uc?id=1VRJc1BM2651YMxTvir1eQSOOvDgBH-C-&export=download","status":"completed","format":"Youtube Thumbnail","suitability":["mobile"],"folder":"https://drive.google.com/drive/folders/1nFMnnIC1hXe61KiFQebMaTxfhxpWbY53","studioName":"iStar","createdAt":1567158156536,"updatedAt":1588959496031,"acceptedAt":1570731601899,"attributedAt":1588959414830,"keywords":{"en":["blog","browsing","business","woman","computer","creativity","device","digital","freelance","freelancer","icons","internet","laptop","media","network","online","remote work","social media","web","website","wireless","working","workplace","grey","blue","sofa","youtube","thumbnail"],"ru":["блог","просмотр","бизнес","женщина","компьютер","творчество","устройство","цифровой","фриланс","свободный художник","иконки","интернет","ноутбук","медиа","сеть","онлайн","удаленная робота","социальные медиа","веб","вебсайт","беспроводной","работает","рабочее место","серый","синий","диван"],"uk":["блог","перегляд","бізнес","жінка","комп’ютер","творчість","пристрій","цифровий","позаштатно","фрілансер","іконки","інтернет","ноутбук","медіа","мережа","онлайн","віддалена робота","соціальні медіа","веб","вебсайт","бездротові","працює","робче місце","сірий","синій","диван"],"es":["blog en","navegando","nombre de negocio","mujer e","encendido apagado computadora","cratividad","dispositivo de","dşgital","lanza libre","persona de libre dedicación","íconos","de internet","con portatil","medios de comunicacion antiguos","red de","todos en linea","trabajo a distancia","social medía","web tenemos","tu pagina web","inalambrico","seguimos trabajando","plaza de trabajo","gris","varias azul","en el sillon"],"pt":["blogue","navegação","negócias","mulher a olhar","olhando computador","criacia","dispositivo","digital ex","freelance","trabalhador autônomo","ícons","curso internet","computador portátil","mídias y","rede","curso on line","trabalho remoto","mídia sociais","teia","website deve","sem fio","trabalhandpo","ambiente de trabalho","cinzento","azul d","sofá s"],"nl":["blog","browsing","zakelij","een vrouw","computer en","creativiteit","apparaat","digitaal","freelance","freelancer","iconen zelf hemaakt","internet","laptop s","media gebruik","netwerk","cursus online","afstandswerk","sociaalmedia","web","nieuw website","draadloze","werkend","werkplek","grijs","blauwe achter","zitbank"],"fr":["bloguer","navigation","nouveau commerce","efemé","ordianateur","créativity","dispositif","numã©riques","free-lance","travailleur indépendant","icônes","internet droit","laptop des","médiathèque","network et","cours en ligne","travail a distance","mã©dia sociaux","web droit","nouveau site web","sans fil","travail","poste de travail","gris","rond bleu","canapé lit"],"de":["blog","surfen","geschã¤ftlich","woman das","edv kurs","kreativität","gerät","digital","freiberuflich","freiberufler","icons","i̇nternet","laptop","medien","hnetzwerk","online war","heimarbeit","sozialmedien","netz","webeite","kabellos","arbeiten","arbeitsplatz","grau","blau","sofa"],"it":["blog","navigazione","business prese","donna di spalle","corso computer","creatività","dispositivo","digitali","libero professionista","libero professionista","icone certo","internet i con","il computer portatile","l media","rete","corso on line","lavoro a distanza","sociale  media","web dei","sito we","senza fili","lavora","posto di lavoro","grigio","azzurra","sul divano"],"pl":["blog","przeglądanie","twój biznes","stara kobieta","w komputerze","kreatywność","urzä…dzenie","cyfrowy","wolny zawód","wolny strzelec","pomagamy icons","internetowe","z laptopem","głoska bezdźwięczna","sieć","online","praca zdalna","socjal media","sieć","strona www","bezprzewodowy","pracy","miejsce pracy","szare","niebiesko","sofa"],"tr":["blog","tarama","e iş","kadın","bilgisayar","yaratıcılık","cihaz","dijital","serbest","bağımsız yazar","simgeler","internet","dizüstü","medya","ağ","online biz","uzaktan çalışma","sosyal mesya","ağ","web sitesi","kablosuz","çalışma","i̇ş yeri̇","gri","mavi","kanepe"],"ja":["ブログ","ブラウジング","ビジネス","女性","コンピューター","創造性","端末","デジタル","フリーランス","フリーランサー","アイコン","インターネット","ラップトップ","メディア","通信網","オンライン","リモートワーク","ソーシャルメディア","ウェブ","ウェブサイト","無線","ワーキング","職場","グレー","青い","ソファー"],"cs":["podnikání","počitač","gauč"]},"industries":["businessFinance","educationTraining","techGadgets"],"languages":["en"],"title":"Business Ideas Woman on Sofa Working on Laptop","localizedTitle":{"en":"Business Ideas Woman on Sofa Working on Laptop","ru":"Бизнес идеи женщина на диване работает на ноутбуке","uk":"Бізнес ідеї жінка на дивані працює на ноутбуці","es":"Ideas de negocios Mujer en el sofá trabajando en la computadora portátil","pt":"Mulher de idéias de negócios no sofá trabalhando no laptop","nl":"Zakelijke ideeën vrouw op sofa die op laptop werkt","fr":"Idées d'affaires femme sur canapé travaillant sur ordinateur portable","de":"Geschäftsideen Frau auf Sofa Arbeiten am Laptop","it":"Donna di idee di affari su Sofa Working sul computer portatile","pl":"Pomysły biznesowe Kobieta na kanapie Praca na laptopie","tr":"İş fikirleri kadın kanepede dizüstü bilgisayarda çalışma","ja":"ラップトップに取り組んでいるソファの上のビジネスアイデア女性","cs":"Obchodní nápady žena na pohovce, pracovat na notebooku"},"forSubscribers":true,"language":"en","seoMeta":{"shouldIndex":true}}