{"id":"5d690e79abc8ea6d1c145d48","_id":"5d690e79abc8ea6d1c145d48","name":"Explain science.svg","width":1280,"height":720,"category":"Education & Science","categoryCaption":"educationScience","group":"HC","measureUnits":"px","driveFileIds":["1juAjiOq0Npp0gXEp10jrm1pKHPIhoTcr"],"template":[{"elements":[{"uuid":"oAnLKh5jkFAhJgmQUPVOCaPpnks2ImRIHAq9Tmu9YLLBSJ4MYaVvRxma9h4XBYxS","width":1332,"height":889.2,"angle":0,"originalAngle":0,"id":"5d690e8cabc8ea6d1c148063","innerId":0,"type":"imageElement","templateAsset":true,"position":{"left":124.3,"top":-100.5},"opacity":1,"isSharedProject":true,"mediaAsset":true,"mediaId":"5d690e8cabc8ea6d1c14809b","dphId":"139844446","isFreeItem":false,"flipped":{"horizontal":1,"vertical":1},"isBackground2":false,"hasBackgroundLabel":true,"filters":{"brightness":0,"contrast":0,"saturate":0,"tint":0,"blur":0,"crossProcess":0,"vignette":0},"filtersPreset":false,"filtersPresetIntensity":50,"filtersIntensityEnabled":false,"originalImageWidth":1332,"originalImageHeight":889.2,"cropOpts":{"left":0,"top":0,"width":0,"height":0},"sticky":true},{"uuid":"PRoioAkAfEfX6xHinf68bKMyud8m9aTp4WxAq6JAweUlaFPEJC6W1EDjWGPiyiOo","width":640,"height":720,"angle":0,"originalAngle":0,"id":"5d690e8eabc8ea6d1c148471","innerId":1,"type":"svgElement","templateAsset":true,"position":{"left":0,"top":0},"opacity":1,"isSharedProject":true,"mediaAsset":true,"mediaId":"5d690e8eabc8ea6d1c1484b0","isFreeItem":true,"flipped":{"horizontal":1,"vertical":1},"isBackground2":false,"hasBackgroundLabel":true,"colors":[{"id":0,"color":"#D7191C"}],"newColors":[{"id":0,"color":"#D7191C"}],"special":false},{"uuid":"RLs4zPuXnJ1sjPO2BUK4Z7RdEKraPwatUF70WEcYezfuvVjLpoeJOU0L1SACHSn7","width":411,"height":411,"angle":0,"originalAngle":0,"id":"5d690e8eabc8ea6d1c1483f1","innerId":2,"type":"svgElement","templateAsset":true,"position":{"left":-159,"top":447},"opacity":1,"isSharedProject":true,"mediaAsset":true,"mediaId":"5d690e8eabc8ea6d1c148431","isFreeItem":true,"flipped":{"horizontal":1,"vertical":1},"isBackground2":false,"hasBackgroundLabel":true,"colors":[{"id":0,"color":"#A71A17"}],"newColors":[{"id":0,"color":"#A71A17"}],"special":true},{"uuid":"baoNZb1TiQKy3ye2BNLjsmFNfBU2iNdgN4PS3uyo974zvkP0qXnZRl61WOITnmUK","width":73,"height":73,"angle":0,"originalAngle":0,"id":"5d690e8eabc8ea6d1c148420","innerId":3,"type":"svgElement","templateAsset":true,"position":{"left":433,"top":609},"opacity":1,"isSharedProject":true,"mediaAsset":true,"mediaId":"5d690e8eabc8ea6d1c148452","isFreeItem":true,"flipped":{"horizontal":1,"vertical":1},"isBackground2":false,"hasBackgroundLabel":true,"colors":[{"id":0,"color":"#A71A17"}],"newColors":[{"id":0,"color":"#A71A17"}],"special":true},{"uuid":"jnDRLXEc25Klb413IvKbxG4dn4ZKvxq1438F71lrlQisFUr6diyWf3ZY5imQdaVC","width":342,"height":313,"angle":0,"originalAngle":0,"id":"5d690e8eabc8ea6d1c1484de","innerId":4,"type":"svgElement","templateAsset":true,"position":{"left":-130,"top":483},"opacity":1,"isSharedProject":true,"mediaAsset":true,"mediaId":"5d690e8eabc8ea6d1c1484ec","dphId":"64251625","isFreeItem":false,"flipped":{"horizontal":1,"vertical":1},"isBackground2":false,"hasBackgroundLabel":true,"colors":[{"id":0,"color":"#1A4378"}],"newColors":[{"id":0,"color":"#1A4378"}],"special":false},{"uuid":"Dlt77VTTuJbRzJb7P1ediAGlN5jyT401zbBFrsgckiQT7pJLjE6eDQH2x0z53oQ9","width":411,"height":411,"angle":0,"originalAngle":0,"id":"5d690e9babc8ea6d1c14a0ad","innerId":5,"type":"svgElement","templateAsset":true,"position":{"left":178,"top":-165},"opacity":1,"isSharedProject":true,"mediaAsset":true,"mediaId":"5d690e9babc8ea6d1c14a11d","isFreeItem":true,"flipped":{"horizontal":1,"vertical":1},"isBackground2":false,"hasBackgroundLabel":true,"colors":[{"id":0,"color":"#A71A17"}],"newColors":[{"id":0,"color":"#A71A17"}],"special":true},{"uuid":"WmA3TFuwpVsO0YIVEbXLkIWzZa9eNd9TvIwWuPOGmVSFA71WZjmHEXnBq808DWyA","width":236,"height":646,"angle":0,"originalAngle":0,"id":"5d690e8eabc8ea6d1c1484a4","innerId":6,"type":"svgElement","templateAsset":true,"position":{"left":241,"top":-281},"opacity":1,"isSharedProject":true,"mediaAsset":true,"mediaId":"5d690e8eabc8ea6d1c1484bb","dphId":"64251625","isFreeItem":false,"flipped":{"horizontal":1,"vertical":1},"isBackground2":false,"hasBackgroundLabel":true,"colors":[{"id":0,"color":"#1A4378"}],"newColors":[{"id":0,"color":"#1A4378"}],"special":false},{"uuid":"CzdxH4F4TMdD5vjLgdYiVwCBfVHiEO8yaAdppdY75Az4DKYgvE8Ue773pZ8deMig","width":451.3,"height":54,"angle":0,"originalAngle":0,"id":8,"innerId":7,"type":"textElement","templateAsset":true,"position":{"left":99.97481027104178,"top":580.2699149265275},"opacity":1,"isSharedProject":true,"mediaAsset":false,"isFreeItem":true,"hasBackgroundLabel":true,"text":"TO PRESCHOOLERS","fontSize":54.194260780222464,"font":"Bebas Neue","lineHeight":1,"wordBreak":"breakWord","colorMap":[{"startIndex":0,"type":"color","value":"FFFF00","endIndex":14}],"boldMap":[{"startIndex":0,"type":"bold","value":true,"endIndex":14}],"italicMap":[{"startIndex":0,"type":"italic","value":false,"endIndex":14}],"textAlign":"left","lineMap":[{"startIndex":0,"endIndex":14}],"capitalize":false,"underline":false,"letterSpacing":5.912101176024269},{"uuid":"1oEAuPxnjUYjSdacItoxDn4UveCOgLUJvE5h0EhIxJq5ErSgx2HqwRCcDLVoBdyv","width":531,"height":417,"angle":0,"originalAngle":0,"id":9,"innerId":8,"type":"textElement","templateAsset":true,"position":{"left":96.22209332302137,"top":101.59022944057749},"opacity":1,"isSharedProject":true,"mediaAsset":false,"isFreeItem":true,"hasBackgroundLabel":true,"text":"How to explain science","fontSize":164,"font":"Covered By Your Grace","lineHeight":0.85,"wordBreak":"breakWord","colorMap":[{"startIndex":0,"type":"color","value":"00FFCC","endIndex":21}],"boldMap":[{"startIndex":0,"type":"bold","value":false,"endIndex":21}],"italicMap":[{"startIndex":0,"type":"italic","value":false,"endIndex":21}],"textAlign":"left","lineMap":[],"capitalize":false,"underline":false,"letterSpacing":0},{"uuid":"0Ok8Uq353eenr2qJiCihJvR5FhpfjGBSkkYPGEGrs4rEp5UoUOKWMMKEpysDRkpq","width":383,"height":2,"angle":0,"originalAngle":0,"id":"5d690e8eabc8ea6d1c1483e0","innerId":9,"type":"svgElement","templateAsset":true,"position":{"left":99,"top":559},"opacity":1,"isSharedProject":true,"mediaAsset":true,"mediaId":"5d690e8eabc8ea6d1c148447","isFreeItem":true,"flipped":{"horizontal":1,"vertical":1},"isBackground2":false,"hasBackgroundLabel":true,"colors":[{"id":0,"color":"#FF0"}],"newColors":[{"id":0,"color":"#FF0"}],"special":false},{"uuid":"vM0hz222xvihehkI7NCz2UNYrcfmLnT0MlsDYBwY6Zar5zGtP4bExDSE5cJ8DZF8","width":383,"height":2,"angle":0,"originalAngle":0,"id":"5d690e8eabc8ea6d1c14838e","innerId":10,"type":"svgElement","templateAsset":true,"position":{"left":99,"top":645},"opacity":1,"isSharedProject":true,"mediaAsset":true,"mediaId":"5d690e8eabc8ea6d1c148408","isFreeItem":true,"flipped":{"horizontal":1,"vertical":1},"isBackground2":false,"hasBackgroundLabel":true,"colors":[{"id":0,"color":"#FF0"}],"newColors":[{"id":0,"color":"#FF0"}],"special":false}],"pageNumber":0}],"templateType":"regular","hash":"1WKy1mtVxW_MFj09X47iCgkn3c--Me3U5","pixelWidth":1280,"pixelHeight":720,"previewImageUrls":["/common/9cde3180-fb11-4792-a850-e7d4dd596f81.jpg"],"hasAnimatedPreview":false,"hasAnimatedScreenPreview":false,"downloadUrl":"https://drive.google.com/uc?id=1juAjiOq0Npp0gXEp10jrm1pKHPIhoTcr&export=download","status":"completed","format":"Youtube Thumbnail","suitability":["mobile"],"folder":"https://drive.google.com/drive/folders/1WKy1mtVxW_MFj09X47iCgkn3c--Me3U5","studioName":"iStar","createdAt":1567166073279,"updatedAt":1588921217387,"acceptedAt":1570730962474,"attributedAt":1588921198059,"keywords":{"en":["biology","chemistry","children","classroom","education","equipment","experiment","invention","kids","lab","laboratory","microscope","red","school","science","scientific","yellow","youtube","thumbnail"],"ru":["биология","химия","дети","школьный класс","образование","оборудование","эксперимент","изобретение","детки","лабораторный","лаборатория","микроскоп","красный","школа","наука","научная","желтый"],"uk":["біологія","хімія","діти","клас","освіта","устаткування","експеримент","винахід","дітки","лабораторний","лабораторія","мікроскоп","червоний","школа","наука","науковий","жовтий"],"es":["biología","para química","niños en una ronda","aula de clase","educación a","equipamiento","experimentar","invento","peques","laboratorio","laboratiorio","microoscopio","x roja","volver al cole","r ciencia","cienctifico","amarillass"],"pt":["biologia","curso de química","infantojuvenil","sala  de aula","educã§ã£o","equipajea","experimentar","invenã§ã£o","cranças","laboratório","laboratã³rio","microscópio","mais vermelho","para escola","ciência","cientifica","amarelho"],"nl":["biologie","scheikunde","children of dat","klas","onderwij","uitrusting","experimenteren","uitvinding","kids dat","laboratorium","laboratorium","microscoop","rode","voor school","wteenschap","wetenschapelijke","gele"],"fr":["la biologie","chimie","aide aux enfants","salle de cours","droit à léducation","ã©quipement d","expérience","invention","gamins","laboratoire","laboratoire","microscope","cours red","la rentrée des classes","science faire","scientifique","jaune"],"de":["biologie","keine chemie","für kinder","klassenzimmer","weiterbildung","ausrüstung","experiment","erfindung","kinder","labor","labor","mikroskop","rotes x","schul","wissenschaft","wissenschaftliches","gelb"],"it":["biologia","chimica","salite bambini","aula","formazione scolastica","apparecchiature","sperimentare","invenzione","ragazzini","laboratorio","laboratorio","microsocopio","rosso e","scuola ok","scienza","scientifici","giallo"],"pl":["biologia","chemia","dziecięce","klasa szkolna","edukacja","sprzęt","eksperyment","wynalazek","dzieciaki","laboratorium","laboratorium","mikroskop","czerwone","szkolny","nauka","naukowe","żółty"],"tr":["biyoloji","kimya","çocuklar","derslik","e eğitim","gereç","deney","icat","çocuklar","laboratuvar","laboratuvar","mikroskop","kırmızı","mektep","bılım","bilimsel","sarı"],"ja":["生物学","化学","子供達","教室","教育","装置","実験","発明","子供たち","ラボ","実験室","顕微鏡","赤","学校","理科","科学的","黄"],"cs":[]},"industries":["educationTraining","familyKids"],"languages":["pt"],"title":"Science Education Kids in Laboratory","localizedTitle":{"en":"Science Education Kids in Laboratory","ru":"Наука Образование Дети в лаборатории","uk":"Навчальна освіта дітей у лабораторії","es":"Niños de educación científica en laboratorio","pt":"Crianças da educação científica no laboratório","nl":"Science Education Kids in Laboratory","fr":"Enseignement des sciences pour les enfants en laboratoire","de":"Wissenschaftspädagogik Kinder im Labor","it":"Scienza Istruzione Bambini in laboratorio","pl":"Nauka Edukacja dzieci w laboratorium","tr":"Laboratuvarda Fen Eğitimi Çocukları","ja":"実験室の科学教育の子供","cs":"Vědecké vzdělávání dětí v laboratoři"},"forSubscribers":true,"language":"en","seoMeta":{"shouldIndex":true}}