{"id":"60af63eda637ee11e33c3d0d","_id":"60af63eda637ee11e33c3d0d","name":"Summer Four.svg","width":1280,"height":720,"category":"Leisure & entertainment","categoryCaption":"leisureEntertainment","group":"HC","measureUnits":"px","driveFileIds":["1QDoPzPMz6VmyPJ7itKzh11_X80jnP0Of"],"removed":false,"template":[{"animationMode":"elements","customAnimationDuration":0,"elements":[{"top":-1.0000000000000195,"left":0.9523808814490309,"width":1280,"height":720,"angle":0,"uuid":"WDs9WNSpnsvqr2Sao8yoNZpVDwTecJfrl9AYDKU7dwhP0ZlFsoDFNvV3DlXIB9rJ","mediaId":"60af92b3a637ee11e3331b76","opacity":1,"flipHorizontal":1,"flipVertical":1,"type":"svgElement","locked":false,"colors":[{"id":0,"color":"#F59517"}],"position":{"left":0.9523808814490309,"top":-1.0000000000000195}},{"top":171.00000000000003,"left":0.9523808814490309,"width":350,"height":438,"angle":0,"uuid":"ZPIRaqInVt9N05OIQW7F6gXKYAZ4MzzwrV0s6n6Q7wSQohVHTXcwvcVR7O6dNNuh","mediaId":"60af63f1a637ee11e33c555d","opacity":1,"flipHorizontal":1,"flipVertical":1,"type":"maskElement","locked":false,"dphId":"407081740","filters":{"brightness":0,"contrast":0,"saturate":0,"tint":0,"blur":0,"crossProcess":0,"vignette":0},"filtersIntensityEnabled":false,"filtersPresetIntensity":50,"elements":[{"type":"imageElement","uuid":"ZPIRaqInVt9N05OIQW7F6gXKYAZ4MzzwrV0s6n6Q7wSQohVHTXcwvcVR7O6dNNuh-sticked","left":-255,"top":-11,"width":686.51,"height":457.67,"opacity":1,"angle":0,"flipHorizontal":1,"flipVertical":1,"originalImageWidth":686.51,"originalImageHeight":457.67,"cropOpts":{"left":0,"top":0,"width":686.51,"height":457.67},"filters":{"brightness":0,"contrast":0,"saturate":0,"tint":0,"blur":0,"crossProcess":0,"vignette":0},"filtersIntensityEnabled":false,"filtersPresetIntensity":50,"mediaId":"60af92b3a637ee11e3331eec","locked":false,"position":{"left":-255,"top":-11}}],"maskType":"svg","maskData":{"dimensions":{"width":350,"height":438,"left":0,"top":190}},"colors":[{"id":0,"color":"none"}],"position":{"left":0.9523808814490309,"top":171.00000000000003}},{"top":171.00000000000003,"left":930.952380881449,"width":350,"height":438,"angle":0,"uuid":"JzS3boTKuqSIMja6nKMt22oHp6e8IykT5GUClhXTTDS3CwOt8Y6uaUoW4mNJpg0g","mediaId":"60af63f1a637ee11e33c556f","opacity":1,"flipHorizontal":1,"flipVertical":1,"type":"maskElement","locked":false,"dphId":"245049560","filters":{"brightness":0,"contrast":0,"saturate":0,"tint":0,"blur":0,"crossProcess":0,"vignette":0},"filtersIntensityEnabled":false,"filtersPresetIntensity":50,"elements":[{"type":"imageElement","uuid":"JzS3boTKuqSIMja6nKMt22oHp6e8IykT5GUClhXTTDS3CwOt8Y6uaUoW4mNJpg0g-sticked","left":-266,"top":-77,"width":919.51,"height":602.07,"opacity":1,"angle":0,"flipHorizontal":1,"flipVertical":1,"originalImageWidth":919.51,"originalImageHeight":602.07,"cropOpts":{"left":0,"top":0,"width":919.51,"height":602.07},"filters":{"brightness":0,"contrast":0,"saturate":0,"tint":0,"blur":0,"crossProcess":0,"vignette":0},"filtersIntensityEnabled":false,"filtersPresetIntensity":50,"mediaId":"60af92b3a637ee11e3331d08","locked":false,"position":{"left":-266,"top":-77}}],"maskType":"svg","maskData":{"dimensions":{"width":350,"height":438,"left":930,"top":190}},"colors":[{"id":0,"color":"none"}],"position":{"left":930.952380881449,"top":171.00000000000003}},{"top":171.00000000000003,"left":421.952380881449,"width":438,"height":438,"angle":0,"uuid":"kFw8hPPmfj5SvfHpd10FF9FgoOhS6X57yTaU6tkZLluDUDe1Yv8Bhzh0zKnnCB3C","mediaId":"60af63f1a637ee11e33c55ae","opacity":1,"flipHorizontal":1,"flipVertical":1,"type":"maskElement","locked":false,"dphId":"351016318","filters":{"brightness":0,"contrast":0,"saturate":0,"tint":0,"blur":0,"crossProcess":0,"vignette":0},"filtersIntensityEnabled":false,"filtersPresetIntensity":50,"elements":[{"type":"imageElement","uuid":"kFw8hPPmfj5SvfHpd10FF9FgoOhS6X57yTaU6tkZLluDUDe1Yv8Bhzh0zKnnCB3C-sticked","left":-9,"top":-84,"width":455.85,"height":607.8,"opacity":1,"angle":0,"flipHorizontal":1,"flipVertical":1,"originalImageWidth":455.85,"originalImageHeight":607.8,"cropOpts":{"left":0,"top":0,"width":455.85,"height":607.8},"filters":{"brightness":0,"contrast":0,"saturate":0,"tint":0,"blur":0,"crossProcess":0,"vignette":0},"filtersIntensityEnabled":false,"filtersPresetIntensity":50,"mediaId":"60af92b3a637ee11e3331f76","locked":false,"position":{"left":-9,"top":-84}}],"maskType":"svg","maskData":{"dimensions":{"width":438,"height":438,"left":421,"top":190}},"colors":[{"id":0,"color":"none"}],"position":{"left":421.952380881449,"top":171.00000000000003}},{"top":63.99999999999997,"left":310.952380881449,"width":34,"height":43,"angle":0,"uuid":"9tUZygoh1mienjf1ebAB6XMDbonKtA4z5DzD0DWqZHCmDTADvFs7ccqtj3JNPsJJ","mediaId":"60af63f1a637ee11e33c579b","opacity":1,"flipHorizontal":1,"flipVertical":1,"type":"svgElement","locked":false,"colors":[{"id":0,"color":"#FFF"}],"position":{"left":310.952380881449,"top":63.99999999999997}},{"top":640.4999999999998,"left":-48.142857355652914,"width":498,"height":29,"angle":0,"uuid":"TUhvl2Oi1KfTujB4VrokiDmmGZs0SArHCtbzWYZ8gTHwsMieyHj7UIkOR6GttGKy","mediaId":"60af63f1a637ee11e33c56b1","opacity":1,"flipHorizontal":1,"flipVertical":1,"type":"svgElement","locked":false,"colors":[{"id":0,"color":"#FFF"}],"position":{"left":-48.142857355652914,"top":640.4999999999998}},{"top":637.9999999999998,"left":819.952380881449,"width":518,"height":34,"angle":0,"uuid":"9T26Eru9KTEslLlykVIE9YSBwJmFPETnoDV2YS9EwpVw9BVXdOECSXTbrRwB86kE","mediaId":"60af63f1a637ee11e33c5734","opacity":1,"flipHorizontal":1,"flipVertical":1,"type":"svgElement","locked":false,"colors":[{"id":0,"color":"#FFF"}],"position":{"left":819.952380881449,"top":637.9999999999998}},{"top":44.99999999999997,"left":938.952380881449,"width":30,"height":34,"angle":0,"uuid":"bMIPV82S0e3YbQhEO3SPaBmquKWoR2rEPx6HxFCAVspcl8KCzWKhSMfNOte4bwki","mediaId":"60af63f1a637ee11e33c56b8","opacity":1,"flipHorizontal":1,"flipVertical":1,"type":"svgElement","locked":false,"colors":[{"id":0,"color":"#FFF"}],"position":{"left":938.952380881449,"top":44.99999999999997}},{"top":38,"left":1066,"width":317,"height":73,"angle":0,"uuid":"rsDCTj6GYx5vm2AZWSGw3pzZmFUAoDctAfLs4HfNNx2TMS2MJ6ZAZRud17w8AvKK","mediaId":"60af63f1a637ee11e33c56c2","opacity":1,"flipHorizontal":1,"flipVertical":1,"type":"svgElement","locked":false,"colors":[{"id":0,"color":"#FFF"}],"position":{"left":1066,"top":38}},{"top":24.99999999999998,"left":-79.04761911855097,"width":314,"height":101,"angle":0,"uuid":"dD2ytYGqcf5gBpvr4Ttamm2YWKiVi7O2RZLILUuna5WJvVwCLrkqwlvCV98nWypr","mediaId":"60af63f1a637ee11e33c57f6","opacity":1,"flipHorizontal":1,"flipVertical":1,"type":"svgElement","locked":false,"colors":[{"id":0,"color":"#FFF"}],"position":{"left":-79.04761911855097,"top":24.99999999999998}},{"top":207.00000000000003,"left":734.952380881449,"width":272,"height":75,"angle":0,"uuid":"cesNuL7XrHIxA7xNPubMX1pg8vJvTYQnP03ja8bVqXRkHGydOHrcVebEF62iu3IW","mediaId":"60af63f1a637ee11e33c57eb","opacity":1,"flipHorizontal":1,"flipVertical":1,"type":"svgElement","locked":false,"colors":[{"id":0,"color":"#FFF"}],"position":{"left":734.952380881449,"top":207.00000000000003}},{"top":-29.00000000000002,"left":969.952380881449,"width":200,"height":58,"angle":0,"uuid":"J17n9IF5ZopBn01KokKWqKNsNoqnz0bR7JuWtW1aKA2P9a1CzeN40dHy1VrbQFTA","mediaId":"60af63f1a637ee11e33c570a","opacity":1,"flipHorizontal":1,"flipVertical":1,"type":"svgElement","locked":false,"colors":[{"id":0,"color":"#FFF"}],"position":{"left":969.952380881449,"top":-29.00000000000002}},{"top":63.99999999999997,"left":338.45238088144896,"width":601,"height":58,"angle":0,"uuid":"lZrHOqUhdJ0w20b8Bh66XGGhXLX92SbCwUWHhva4QFs73LNED6t3olyzADI2i1Cv","opacity":1,"type":"textElement","locked":false,"fontSize":58,"font":"La Belle Aurore","lineHeight":1,"colorMap":[{"startIndex":0,"endIndex":18,"type":"color","value":"FFFFFF"}],"boldMap":[{"startIndex":0,"endIndex":18,"type":"bold","value":false}],"italicMap":[{"startIndex":0,"endIndex":18,"type":"italic","value":false}],"textAlign":"center","capitalize":false,"letterSpacing":0,"text":"Lazy days of summer","wordBreak":"breakWord","underline":false,"lineMap":[{"startIndex":0,"endIndex":18,"value":"line","type":"line"}],"opacityMap":[{"startIndex":0,"endIndex":18,"type":"opacity","value":1}],"position":{"left":338.45238088144896,"top":63.99999999999997}},{"top":649.9999999999998,"left":476.45238088144896,"width":327,"height":30,"angle":0,"uuid":"qMagnFw6oHQbIDQj0rFe1vKnDcRL89fK0eY10RORs89s1eimW4eYO2NAiS7cUe67","opacity":1,"type":"textElement","locked":false,"fontSize":30,"font":"Sniglet","lineHeight":1,"colorMap":[{"startIndex":0,"endIndex":14,"type":"color","value":"FFFFFF"}],"boldMap":[{"startIndex":0,"endIndex":14,"type":"bold","value":false}],"italicMap":[{"startIndex":0,"endIndex":14,"type":"italic","value":false}],"textAlign":"center","capitalize":false,"letterSpacing":1,"text":"TRAVEL VLOG #15","wordBreak":"breakWord","underline":false,"lineMap":[{"startIndex":0,"endIndex":14,"value":"line","type":"line"}],"opacityMap":[{"startIndex":0,"endIndex":14,"type":"opacity","value":1}],"position":{"left":476.45238088144896,"top":649.9999999999998}}],"uuid":"kxi6QyjjY5u8dPV9BDBnDDhIq3YPhc3tCV1XTeEyhifOnAwIQ8UhpSQWSwTXuLQa","audio":[]}],"templateType":"regular","hash":"1ord2vqd4ekqxkEQ94GpVrtIERrz7qOok","pixelWidth":1280,"pixelHeight":720,"previewImageUrls":["/downloads/652ae0ba-0acb-4c29-a6be-a28b241d1b1a.jpeg"],"hasAnimatedPreview":false,"hasAnimatedScreenPreview":false,"downloadUrl":"https://drive.google.com/uc?id=1QDoPzPMz6VmyPJ7itKzh11_X80jnP0Of&export=download","status":"completed","format":"Youtube Thumbnail","suitability":["mobile"],"folder":"https://drive.google.com/drive/folders/1ord2vqd4ekqxkEQ94GpVrtIERrz7qOok","errors":[],"warnings":[],"studioName":"iStar","createdAt":1622107117139,"updatedAt":1622635249945,"acceptedAt":1622119153615,"attributedAt":1622634480540,"keywords":{"en":["summer","travel","tourist","vacation","happy","people","tourism","young","female","beautiful","fun","trip","freedom","leisure","journey","relax","women","happiness","adventure","multiracial","frame","orange","inspiration","inspirational","collage","youth","youtube","thumbnail"],"de":["sommer","reisen fã¼r immer","ferien","du machst mich glücklich","leute","tourismus","jung","weiblich","schön","spass","freiheit","freizeit","chillen","frauen","rahmen rund"],"fr":["été last","voyager","touriste","vacanc","contente","personnes qui s'interrogent","tourisme","jeune","belle","voyage","liberté","loisir","fimmes","bonheur","aventure","encadrer","inspirational qui","jeunesse c"],"el":["καλοκαιρι","travel to","πλαισιο","kolaz"],"es":["estio","para viaje","turístico","vacacionar","felíz","varias personas","turismo","viejos y jóvenes","fémina","esitloso","no hay diversión","tropezar","libertad y voluntad","ocio","relajar","mujerees","felicidad","aventura","desencuadre","media naranja","inspiracion","inspiracionales","collage de dos","para juventud","haber de youtube"],"ru":["летнее","путешесьвие","отпуск","быть счастливой","людт","туризм","молодой","женские","красивое","весело","поездка","активный отдых","путтешествие","расслабиться","женщины в ит","счастья","рамка круглая с облочком","оранжеый","вдохновенин","колладж","молодеж","ютьюб"],"it":["viaggiare","contenti","conoscere persone","anziana e giovane","bello","divertimento","gita","svago","tragitto","donne","felicità","multirazziale","portafoto","arancione","gioventù"],"hu":["nyári","emberek","keret","narancs","inspiráció"],"pt":["verao","viajem","férias","felizcidades","pessoas velhas","velhos e jovens","femininos","bonitos","sarro","iagem","liberdade","lazer e","relaxe","sexo feminino","felicidade","moldura e","cor de laranja","inspiracao","colagem","juventude","outro na youtube"],"pl":["podróży","turystyczn","dwie osoby","turystyka","płeć żeńska","zabawy","wycieczka zagraniczna","podróż","kobiety","szczęścia","przygoda","pomarańcza","inspiracja","kolaż","młodzież","miniaturka"],"nl":["zomer","reizen","gelukkig","twee mensen","toerisme","jong en oud","niet leuk","van trip","vrijheid","kom tot rust","dames","rond frame","appelsien","inspiratie","inspirerende","collage maken","jeugd"],"ja":["夏","旅行","ツーリスト","リラックス","枠","ひらめき","サムネイル"],"cs":["léto","cestovka","šťastný","dva lidi","legrace","výlet","volný čas","rameček","pomeranč","koláž"],"tr":["yaz","seyehat","turist","mutlu  yüz","iki kişi","turizm","genç","güzel","özgürlük","kadınlr gibi","mutluluk","yuvarlak cerçeve","portakal","ilhan","kolaj","gençler"],"uk":["літо","подорожі назавжди","відпочинок","щасливого","люді","молодь","найкрасивіші","жінки","щастя","пригода","рамк","оранжевий","для ютуба"],"mx":["estio","para viaje","turístico","vacacionar","felíz","varias personas","turismo","viejos y jóvenes","fémina","esitloso","no hay diversión","tropezar","libertad y voluntad","ocio","relajar","mujerees","felicidad","aventura","desencuadre","media naranja","inspiracion","inspiracionales","collage de dos","para juventud","haber de youtube"]},"industries":["entertainmentLeisure","travelTourism"],"title":"Summer Travelling Inspiration with Beautiful Girls","localizedTitle":{"en":"Summer Travelling Inspiration with Beautiful Girls","de":"Reiseinspiration für den Sommer mit schönen Mädchen","fr":"Inspiration de voyage d'été avec de belles filles","el":"Καλοκαίρι ταξίδια έμπνευσης με όμορφα κορίτσια","es":"Inspiración de viaje de verano con chicas guapas","ru":"Вдохновение для летних путешествий с красивыми девушками","it":"Ispirazione per i viaggi estivi con belle ragazze","hu":"Nyári utazási inspiráció gyönyörű lányokkal","pt":"Inspiração de viagem de verão com lindas garotas","pl":"Letnia inspiracja podróżnicza z pięknymi dziewczynami","nl":"Zomerse reisinspiratie met mooie meiden","ja":"美少女との夏の旅のインスピレーション","cs":"Letní putovní inspirace s krásnými dívkami","tr":"Güzel kızlarla yaz seyahat ilhamı","uk":"Літнє подорож натхнення з красивими дівчатами","mx":"Inspiración de viaje de verano con chicas guapas"},"forSubscribers":true,"v2":true,"language":"en","seoMeta":{"shouldIndex":true}}