{"id":"60f8066b8070ea8a9ba7f797","_id":"60f8066b8070ea8a9ba7f797","name":"fun_3.svg","width":1280,"height":720,"category":"Leisure & entertainment","categoryCaption":"leisureEntertainment","group":"HC","measureUnits":"px","driveFileIds":["1q_XiSuIsu7nrqt4j_PQgKDC8FowAcJ2S"],"removed":false,"template":[{"animationMode":"elements","customAnimationDuration":0,"elements":[{"top":-174,"left":-56,"width":1339,"height":894,"angle":0,"uuid":"DFcsXSHI9DPuMQJRo7W2vdp9wjtoT5ZM4FRz9CaEMOAFeTAdvMZVlObR8ucAZRLe","mediaId":"60f8067c8070ea8a9ba84e13","opacity":1,"flipHorizontal":1,"flipVertical":1,"isBackground":true,"type":"imageElement","locked":false,"dphId":"155420360","filters":{"brightness":0,"contrast":0,"saturate":0,"tint":0,"blur":0,"crossProcess":0,"vignette":0},"filtersIntensityEnabled":false,"filtersPresetIntensity":50,"originalImageWidth":1338.3,"originalImageHeight":893.09,"cropOpts":{"top":0,"left":0,"width":0,"height":0},"position":{"left":-56,"top":-174}},{"top":-160.21052631578948,"left":262.10526315789474,"width":773,"height":720,"angle":0,"uuid":"XiiZbgnQ2FTPC9xu590INZijvqtt2PQHTKwV73bTDa3glTPfIXxoSGhaefR1f38d","mediaId":"60f8067c8070ea8a9ba84b08","opacity":1,"flipHorizontal":1,"flipVertical":1,"type":"maskElement","locked":false,"dphId":"138315728","filters":{"brightness":0,"contrast":0,"saturate":0,"tint":0,"blur":0,"crossProcess":0,"vignette":0},"filtersIntensityEnabled":false,"filtersPresetIntensity":50,"elements":[{"type":"imageElement","uuid":"XiiZbgnQ2FTPC9xu590INZijvqtt2PQHTKwV73bTDa3glTPfIXxoSGhaefR1f38d-sticked","left":-81,"top":-15,"width":1001.64,"height":751.12,"opacity":1,"angle":0,"flipHorizontal":1,"flipVertical":1,"originalImageWidth":1001.64,"originalImageHeight":751.12,"cropOpts":{"left":0,"top":0,"width":1001.64,"height":751.12},"filters":{"brightness":0,"contrast":0,"saturate":0,"tint":0,"blur":0,"crossProcess":0,"vignette":0},"filtersIntensityEnabled":false,"filtersPresetIntensity":50,"mediaId":"60f8067d8070ea8a9ba8512b","locked":false,"position":{"left":-81,"top":-15}}],"maskType":"svg","maskData":{"dimensions":{"width":773,"height":720,"left":260,"top":-156}},"colors":[{"id":0,"color":"none"}],"position":{"left":262.10526315789474,"top":-160.21052631578948}},{"top":344,"left":-5,"width":600,"height":137,"angle":0,"uuid":"TU0cnGd9aLcFyf6Qi86nQhpFkBduQakgC4W04bgO9dwkFzMcdPZTdtbEz3OrqAcm","mediaId":"60f8067c8070ea8a9ba84bbc","opacity":1,"flipHorizontal":1,"flipVertical":1,"type":"svgElement","locked":false,"colors":[{"id":0,"color":"#ffda29","opacity":1}],"position":{"left":-5,"top":344}},{"top":480,"left":-5,"width":587,"height":144,"angle":0,"uuid":"6vB0frcNNgHgYLY37OjzSnw8oOcqBaS3RPB5TZpBYXvJOdmnvzm94GgIJPDIyvny","mediaId":"60f8067c8070ea8a9ba84c27","opacity":1,"flipHorizontal":1,"flipVertical":1,"type":"svgElement","locked":false,"colors":[{"id":0,"color":"#ffda29","opacity":1}],"position":{"left":-5,"top":480}},{"top":517.5263157894736,"left":98,"width":485,"height":96,"angle":0,"uuid":"HsqimJNkrjn1wwDnh0qn0lGMTw4PL8392SmE1n4RaCfYJBIS7C1GLUPuodePzXZ9","opacity":1,"type":"textElement","locked":false,"fontSize":96,"font":"Bangers","lineHeight":1,"colorMap":[{"startIndex":0,"endIndex":8,"type":"color","value":"FF3366"}],"boldMap":[{"startIndex":0,"endIndex":8,"type":"bold","value":false}],"italicMap":[{"startIndex":0,"endIndex":8,"type":"italic","value":false}],"textAlign":"left","capitalize":false,"letterSpacing":0,"text":"midsummer","wordBreak":"breakWord","underline":false,"lineMap":[{"startIndex":0,"endIndex":8,"value":"line","type":"line"}],"opacityMap":[{"startIndex":0,"endIndex":8,"type":"opacity","value":1}],"position":{"left":98,"top":517.5263157894736}},{"top":367,"left":80,"width":517,"height":91,"angle":0,"uuid":"rvPlWNmVd4iRxKVVnKQTI3hvS8C3EbexqRfbpfevVa2pUigjEuUhOaoKtHfmNwNp","opacity":1,"type":"textElement","locked":false,"fontSize":91,"font":"Bangers","lineHeight":1,"colorMap":[{"startIndex":0,"endIndex":13,"type":"color","value":"FF3366"}],"boldMap":[{"startIndex":0,"endIndex":13,"type":"bold","value":false}],"italicMap":[{"startIndex":0,"endIndex":13,"type":"italic","value":false}],"textAlign":"left","capitalize":false,"letterSpacing":0,"text":"IT smells like","wordBreak":"breakWord","underline":false,"lineMap":[{"startIndex":0,"endIndex":13,"value":"line","type":"line"}],"opacityMap":[{"startIndex":0,"endIndex":13,"type":"opacity","value":1}],"position":{"left":80,"top":367}}],"uuid":"ajybiuSPCuAIIQl2a1CrKafXP4algvuQiNHq2pYjEALhnyNvmXsdr4Qit5w8t8OA","audio":[]}],"templateType":"regular","hash":"1AfhYNi03YeKo9sUp-3JDZ0X0lI12aA7u","pixelWidth":1280,"pixelHeight":720,"previewImageUrls":["/downloads/01d82978-7c12-4726-8e9b-cd996e4f5b18.jpeg"],"hasAnimatedPreview":false,"hasAnimatedScreenPreview":false,"downloadUrl":"https://drive.google.com/uc?id=1q_XiSuIsu7nrqt4j_PQgKDC8FowAcJ2S&export=download","status":"completed","format":"Youtube Thumbnail","suitability":["mobile"],"folder":"https://drive.google.com/drive/folders/1AfhYNi03YeKo9sUp-3JDZ0X0lI12aA7u","errors":[],"warnings":[],"studioName":"iStar","createdAt":1626867307957,"updatedAt":1630570928574,"acceptedAt":1626867463256,"attributedAt":1626964350781,"keywords":{"en":["cute","cat","animal","nose","kitty","funny","kitten","face","head","pet","illustration","meow","fun","adorable","eyes","donut","sniffing","sweet","food","donut","cake","dessert","pink","sugar","pastry","bakery","glazed","doughnut","colorful","tasty","sprinkles","delicious","dough","snack","glaze","treat","dizzy","humor","humorous","youtube","thumbnail","meme"],"de":["niedlich","katze","tier","nase","kätzchen","lustig","jungtier","gesicht","kopf","heimtier","illustration","miau","spaß","entzückend","augen","donut","schnüffeln","süß","lebensmittel","donut","kuchen","dessert","rosa","zucker","konditorei","bäckerei","glasiert","krapfen","bunt","lecker","streusel","köstlich","teig","imbiss","glasur","leckereien","schwindelfrei","humor","humorvoll","youtube","miniaturansicht","meme"],"fr":["mignon","chat","animaux","nez","minou","c'est drôle","chaton","visage","tête","animaux de compagnie","illustration","miaou !","amusant","adorable","yeux","beignet","renifler","doux","produits alimentaires","beignet","gâteau","dessert","rose","sucre","pâtisserie","boulangerie","émaillés","beignet","coloré","savoureux","saupoudrer","délicieux","pâte","collation","glaçure","traiter","étourdissements","humour","humoristique","youtube","vignette","mème"],"el":["χαριτωμένο","γάτα","ζώο","μύτη","γατούλα","αστείο","γατούλα","πρόσωπο","κεφαλή","κατοικίδιο ζώο","απεικόνιση","νιαούρισμα","διασκέδαση","αξιαγάπητη","μάτια","ντόνατ","εισπνοή","γλυκό","τρόφιμα","ντόνατ","κέικ","επιδόρπιο","ροζ","ζάχαρη","ζαχαροπλαστική","αρτοποιείο","υαλοπίνακας","καρύδι","πολύχρωμο","νόστιμο","ψεκάζει","πεντανόστιμο","ζύμη","σνακ","γάνωμα","θεραπεία","ντίζι","χιούμορ","αστείο","youtube","μικρογραφία","μεμέ"],"es":["lindo","gato","animales","nariz","gatito","gracioso","gatito","cara","cabeza","mascotas","ilustración","¡miau!","diversión","adorable","ojos","rosquilla","olfateando","dulce","alimentos","rosquilla","tarta","postre","rosa","azúcar","pastelería","panadería","acristalado","donut","colorido","sabroso","espolvoreos","delicioso","masa","merienda","esmalte","tratar","mareado","humor","humorístico","youtube","miniatura","meme"],"ru":["симпатичный","кот","животное","нос","китти","смешно","котенок","лицо","глава","животное","иллюстрация","мяу","веселье","очаровательны","глаза","пончик","нюхание","свит","еда","пончик","торт","десерт","розовый","сахар","кондитеры","пекарня","ослаблены","пончик","красочный","вкусно","спринтеры","вкусное","тесто","закуски","озил","лечить","диззи","юмор","юмористический","youtube","эскиз","мем"],"it":["carino","gatto","animali","naso","gattino","divertente","gattino","faccia","testa","animali da compagnia","illustrazione","miao","divertimento","adorabile","occhi","ciambella","annusare","dolce","cibo","ciambella","torta","dessert","rosa","zucchero","pasticceria","panificio","smaltato","ciambella","colorato","gustoso","spruzzi","delizioso","pasta","spuntino","smalto","trattare","vertigini","umorismo","umorismo","youtube","miniatura","regime"],"hu":["cuki","macska","állatok","orr","kiscica","vicces","kiscica","arc","fej","kedvtelésből","illusztráció","miaú","szórakozás","imádnivaló","szemek","fánk","szaglászás","édes","élelmiszer","fánk","torta","desszert","rózsaszín","cukor","péksütemény","pékség","üvegezett","fánkot","színes","finom","hinti","finom","tészta","falatkák","máz","kezelés","szédülés","humor","humoros","youtube-ról","hüvelykujj","én én"],"pt":["bonito","gato","animais","nariz","gatinho","engraçado","gatinho","rosto","cabeça","mascote","ilustração","miau","diversão","adorável","olhos","donut","farejar","doce","alimentos","donut","bolo","sobremesa","rosa","açúcar","pastelaria","padaria","vidrado","donut","colorido","saboroso","polvilhas","delicioso","massa de farinha","lanche","esmalte","tratar","tonturas","humor","humoroso","youtube","miniatura","meme"],"pl":["słodkie","kot","zwierzęta","nos","kociak","śmieszne","kociak","twarz","głowa","zwierzęta domowe","ilustracja","meow","zabawa","urocze","oczy","pączek","wąchanie","słodko","żywność","pączek","ciasto","deser","różowy","cukier","ciasto","piekarnia","przeszklone","pączek","kolorowe","smaczne","posypka","pyszne","ciasto","przekąska","szkliwo","leczyć","zawroty głowy","humor","żartowniś","youtube przewodniczący","miniaturka","cynk"],"nl":["schattig","kat","dierlijk","neus","poesje","grappig","poesje","gezicht","hoofd","huisdier","illustratie","meow","plezier","aanbiddelijk","ogen","donut","snuiven","zoet","levensmiddelen","donut","taart","dessert","roze","suiker","gebak","bakkerij","geglazuurd","donut","kleurrijk","lekker","hagelslag","heerlijk","deeg","tussendoortje","glazuur","behandelen","duizelig","humor","humorvol","youtube","miniatuur","meme"],"ja":["かわいい","猫","動物","鼻","子猫ちゃん","面白いね","子猫","顔","頭","ペット","イラスト","ニャー","楽しさ","愛らしい","目","ドーナツ","嗅ぎながら","甘い","食べ物","ドーナツ","ケーキ","デザート","ピンク","砂糖","ペイストリー","パン屋","釉掛け","ドーナッツ","カラフルだ","おいし","振りかける","おいしい","生地","おやつ","釉薬","治療","めまいがする","ユーモア","ユーモアのある","奥林匹亚","サムネイル","ミーム"],"cs":["roztomilý","kočka","zvíře","nos","koťátko","vtipné","kotě","tvář","hlava","domácí mazlíčci","ilustrace","mňoukat","zábava","rozkošný","oči","kobliha","čichání","sladké","jídlo","kobliha","dort","dezert","růžová","cukr","pečivo","pekárna","zasklené","kobliha","barevné","chutné","kropení","lahodné","těsto","svačinka","glazura","léčbě","závratě","humor","vtipný","youtube","miniatura","motiv"],"tr":["şirin","kedi","hayvan","burun","kedicik","komik","yavru kedi","yüz","başı","evcil hayvan","resimleme","miyav","eğlenceli","tapılası","gözler","çörek","kokuyor","tatlı","yiyecek","çörek","kek","tatlı","pembe","şeker","hamur işi","fırın","cilalı","çörek","renkli","lezzetli","fog","lezzetli","hamur","yiyecek","cilala","ikram","başım dönüyor","mizah","komik","youtube","küçük resim","meme"],"uk":["мило","кішка","тварина","ніс","кітті","смішно","кошеня","обличчя","голова","домашня тварина","приклад","мяу","розваги","милий","очі","понт","понюхати","солодкий","їжа","понт","торт","десерт","рожевий","цукор","пестре","пекарня","глазурована","даґнут","барвистий","смакота","бризкає","смачна","тісто","перекусити","глазур","страва","запаморочення","гумор","гумор","youtube","ніготь","мем"],"mx":["lindo","gato","animales","nariz","gatito","gracioso","gatito","cara","cabeza","mascotas","ilustración","¡miau!","diversión","adorable","ojos","rosquilla","olfateando","dulce","alimentos","rosquilla","tarta","postre","rosa","azúcar","pastelería","panadería","acristalado","donut","colorido","sabroso","espolvoreos","delicioso","masa","merienda","esmalte","tratar","mareado","humor","humorístico","youtube","miniatura","meme"]},"industries":["entertainmentLeisure","foodBeverages","petsAnimals"],"title":"Funny Kitty sniffing Donut","localizedTitle":{"en":"Funny Kitty sniffing Donut","de":"Lustige Kitty schnüffelt Donut","fr":"Donut reniflant drôle de Kitty","el":"Αστείο γατάκι ρουθουνίσματος","es":"Donut olfateando gatito divertido","ru":"Смешной котенок нюхает пончик","it":"Ciambella che annusa il gattino divertente","hu":"Vicces Kitty fánkot szimatol","pt":"Kitty farejando donut engraçado","pl":"Zabawna Kitty wąchająca pączek","nl":"Funny Kitty snuift donut","ja":"面白いキティのスニッフィングドーナツ","cs":"Legrační Kitty čichající koblihu","tr":"Komik pisi çörek koklama","uk":"Смішна Кітті нюхає пампушку","mx":"Donut olfateando gatito divertido"},"forSubscribers":true,"v2":true,"language":"en","seoMeta":{"shouldIndex":true}}