{"id":"6135db3a8070ea8a9b0add6a","_id":"6135db3a8070ea8a9b0add6a","name":"personal_01.svg","width":1280,"height":720,"category":"Business & Finance","categoryCaption":"businessFinance","group":"HC","measureUnits":"px","driveFileIds":["1SHTD42pssKP3DP8FydkL0QpwVOWrsLRH"],"removed":false,"template":[{"animationMode":"elements","customAnimationDuration":0,"elements":[{"top":-179,"left":-93,"width":1456,"height":1104,"angle":0,"uuid":"UBefVM8JpKZR29X0sOP7nK1lgPoGjiRmpCwjbHmn9Xxqjz2IVRDkDae17iVg6rFS","mediaId":"6135db468070ea8a9b0b1689","opacity":1,"flipHorizontal":1,"flipVertical":1,"isBackground":true,"type":"imageElement","locked":false,"dphId":"463410252","filters":{"brightness":0,"contrast":0,"saturate":0,"tint":0,"blur":0,"crossProcess":0,"vignette":0},"filtersIntensityEnabled":false,"filtersPresetIntensity":50,"originalImageWidth":1455.75,"originalImageHeight":1103.37,"cropOpts":{"top":0,"left":0,"width":0,"height":0},"position":{"left":-93,"top":-179}},{"top":343,"left":141,"width":997,"height":91,"angle":0,"uuid":"HuD56IU0owhjA40xmZJvJeNgU1dE1Vua74SG8TUf5apIOiKnOdPY0FqdAatMCqiH","mediaId":"6135db448070ea8a9b0b0c7f","opacity":1,"flipHorizontal":1,"flipVertical":1,"type":"svgElement","locked":false,"colors":[{"id":0,"color":"#FFF"},{"id":1,"color":"#D2D2D2"},{"id":2,"color":"#EED236"}],"position":{"left":141,"top":343}},{"top":282,"left":595,"width":89,"height":20,"angle":0,"uuid":"eKlkywz8aINbWTmFFO6VsLS0r6tEBkdd48bOqiAtRd9RVfxpTkMye27kNTpKC5UP","mediaId":"6135db448070ea8a9b0b0d8b","opacity":1,"flipHorizontal":1,"flipVertical":1,"type":"svgElement","locked":false,"colors":[{"id":0,"color":"#FFF"},{"id":1,"color":"#F25F00"}],"position":{"left":595,"top":282}},{"top":262,"left":480,"width":339,"height":292,"angle":0,"uuid":"HnpBvMfLYMyqS8VHJ5Ar3yZcCf74BMYhQ3vuhqYrCn8ZsAmj1dN2rR8VBJXRVZCg","mediaId":"6135db448070ea8a9b0b0ed6","opacity":1,"flipHorizontal":1,"flipVertical":1,"type":"imageElement","locked":false,"dphId":"463410252","filters":{"brightness":0,"contrast":0,"saturate":0,"tint":0,"blur":0,"crossProcess":0,"vignette":0},"filtersIntensityEnabled":false,"filtersPresetIntensity":50,"originalImageWidth":338.16,"originalImageHeight":291.36,"cropOpts":{"top":0,"left":0,"width":0,"height":0},"position":{"left":480,"top":262}},{"top":278,"left":141,"width":138,"height":28,"angle":0,"uuid":"SP4W6wcXsjB3bV8c8nW9YC1RZ7nhTGOl61Z1y0JeXVhEK8eiRzLsmJwrNJ5wdmdV","opacity":1,"type":"textElement","locked":false,"fontSize":28,"font":"V T323","lineHeight":1,"colorMap":[{"startIndex":0,"endIndex":6,"type":"color","value":"FFFFFF"}],"boldMap":[{"startIndex":0,"endIndex":6,"type":"bold","value":false}],"italicMap":[{"startIndex":0,"endIndex":6,"type":"italic","value":false}],"textAlign":"left","capitalize":false,"letterSpacing":0,"text":"PODCAST","wordBreak":"breakWord","underline":false,"lineMap":[{"startIndex":0,"endIndex":6,"value":"line","type":"line"}],"opacityMap":[{"startIndex":0,"endIndex":6,"type":"opacity","value":1}],"position":{"left":141,"top":278}},{"top":278,"left":1026,"width":173,"height":28,"angle":0,"uuid":"mC3VbZ2tr6jR9zsf43o4CMIyDfp2mNKqN7bL5vXtOWw5U9wl2d5JJcVzPljfhKdf","opacity":1,"type":"textElement","locked":false,"fontSize":28,"font":"V T323","lineHeight":1,"colorMap":[{"startIndex":0,"endIndex":9,"type":"color","value":"FFFFFF"}],"boldMap":[{"startIndex":0,"endIndex":9,"type":"bold","value":false}],"italicMap":[{"startIndex":0,"endIndex":9,"type":"italic","value":false}],"textAlign":"left","capitalize":false,"letterSpacing":0,"text":"EPISODE 21","wordBreak":"breakWord","underline":false,"lineMap":[{"startIndex":0,"endIndex":9,"value":"line","type":"line"}],"opacityMap":[{"startIndex":0,"endIndex":9,"type":"opacity","value":1}],"position":{"left":1026,"top":278}},{"top":446,"left":141,"width":75,"height":20,"angle":0,"uuid":"44GJ0rmm948XSCRnDP1acprtXarf8prQEAT1y22ghKLREGbWKQ2MdAdZfoXZUH1X","opacity":1,"type":"textElement","locked":false,"fontSize":20,"font":"V T323","lineHeight":1,"colorMap":[{"startIndex":0,"endIndex":4,"type":"color","value":"FFFFFF"}],"boldMap":[{"startIndex":0,"endIndex":4,"type":"bold","value":false}],"italicMap":[{"startIndex":0,"endIndex":4,"type":"italic","value":false}],"textAlign":"left","capitalize":false,"letterSpacing":0,"text":"06:21","wordBreak":"breakWord","underline":false,"lineMap":[{"startIndex":0,"endIndex":4,"value":"line","type":"line"}],"opacityMap":[{"startIndex":0,"endIndex":4,"type":"opacity","value":1}],"position":{"left":141,"top":446}},{"top":446,"left":1098,"width":63,"height":20,"angle":0,"uuid":"xP3RtIdU3bvhbrw2gfjuKtNGwWnlWL2dNGlLMWrbMiifPTYUyQrWOLT07z2FpTWg","opacity":1,"type":"textElement","locked":false,"fontSize":20,"font":"V T323","lineHeight":1,"colorMap":[{"startIndex":0,"endIndex":4,"type":"color","value":"FFFFFF"}],"boldMap":[{"startIndex":0,"endIndex":4,"type":"bold","value":false}],"italicMap":[{"startIndex":0,"endIndex":4,"type":"italic","value":false}],"textAlign":"left","capitalize":false,"letterSpacing":0,"text":"34:09","wordBreak":"breakWord","underline":false,"lineMap":[{"startIndex":0,"endIndex":4,"value":"line","type":"line"}],"opacityMap":[{"startIndex":0,"endIndex":4,"type":"opacity","value":1}],"position":{"left":1098,"top":446}},{"top":76.66666666666666,"left":384,"width":512,"height":162,"angle":0,"uuid":"T4d377r6jwSs9NwTQm6yhZI1JphUVeE5CG6wFVDJFOP12mGyIblu4uofKkFBVUAN","opacity":1,"type":"textElement","locked":false,"fontSize":112,"font":"V T323","lineHeight":0.73,"colorMap":[{"startIndex":0,"endIndex":13,"type":"color","value":"ffffff"}],"boldMap":[{"startIndex":0,"endIndex":13,"type":"bold","value":false}],"italicMap":[{"startIndex":0,"endIndex":13,"type":"italic","value":false}],"textAlign":"center","capitalize":false,"letterSpacing":0,"text":"Mental\npabulum","wordBreak":"breakWord","underline":false,"lineMap":[{"startIndex":0,"endIndex":5,"value":"line","type":"line"},{"startIndex":6,"endIndex":13,"value":"line","type":"line"}],"opacityMap":[{"startIndex":0,"endIndex":13,"type":"opacity","value":1}],"position":{"left":384,"top":76.66666666666666}}],"uuid":"dYCdUtpkTkWBve2Xmy6rQEF0tcGkyk1HhzEgLOwYdYtdx14J24zUYu1GENUsNqUj","audio":[]}],"templateType":"regular","hash":"16SegoftqfYH3RH9E17k_6HUHinbiWumm","pixelWidth":1280,"pixelHeight":720,"previewImageUrls":["/downloads/0664c3aa-eee3-47df-bcb2-6f2d8ac3a312.jpeg"],"hasAnimatedPreview":false,"hasAnimatedScreenPreview":false,"previewPending":false,"previewUpdatedAt":"2021-09-06T10:02:37.757Z","downloadUrl":"https://drive.google.com/uc?id=1SHTD42pssKP3DP8FydkL0QpwVOWrsLRH&export=download","status":"completed","format":"Youtube Thumbnail","suitability":["mobile"],"folder":"https://drive.google.com/drive/folders/16SegoftqfYH3RH9E17k_6HUHinbiWumm","errors":[],"warnings":[],"studioName":"iStar","createdAt":1630919482025,"updatedAt":1631093172326,"acceptedAt":1630922555217,"attributedAt":1631093172245,"keywords":{"en":["podcast","radio","media","broadcasting","show","communication","broadcast","podcasting","entertainment","talk","mental","health","mental health","woman","girl","tourist","travel","travelling","bus","car","transport","happy","journey","trip","adventure","youtube","thumbnail"],"de":["podcast","radio","medien","ausstrahlung","anzeigen","mitteilung","sendung","podcasting","unterhaltung","gespräch","geistige","gesundheit","psychische gesundheit","frau","mädchen","touristen","reise","reisen","bus","auto","verkehr","glücklich","anreise","reise","abenteuer"],"fr":["podcast","radio","médias","radiodiffusion","spectacle","la communication","diffusion","baladodiffusion","divertissement","parler","mentalement","santé","santé mentale","femme","fille","tourisme","voyages","voyager","autobus","voiture","transports","heureux","voyage","voyage","aventure"],"el":["podcast","ραδιόφωνο","μέσα ενημέρωσης","μετάδοση","εμφάνιση","επικοινωνία","εκπομπή","σημειωση","διασκέδαση","μίλα","ψυχική","υγεία","ψυχικής υγείας","γυναίκα","κορίτσι","τουριστικός","ταξίδι","ταξιδεύοντας","λεωφορείο","αυτοκινητο","μεταφορές","χαρούμενη","ταξίδι","ταξίδι","περιπέτεια"],"es":["podcast","radio","medios de comunicación","retransmisión","mostrar","comunicación","difusión","podcaso","entretenimiento","hablar","mental","sanidad","salud mental","mujer","chica","turista","viajes","viajar","autobus","coche","transporte","feliz","viaje","viaje","aventura"],"ru":["подкаст","радио","сми","вещание","шоу","коммуникация","трансляция","подкастинг","развлечения","говорить","психическое","здоровье","психическое здоровье","женщина","девушка","турист","поездки","путешествия","автобус","авто","транспорт","счастливый","путешествие","поездка","приключение"],"it":["podcast","radio","media","radiodiffusione","mostra","comunicazione","trasmissione","podcasting","spettacolo","parlare","mentale","sanità","salute mentale","donna","ragazza","turista","viaggio","viaggiare","autobus","auto","trasporti","felice","viaggio","viaggio","avventura"],"hu":["podcast","rádió","média","műsorszórás","mutasd!","kommunikáció","közvetítés","pontosítás","szórakoztatás","beszélj","mentális","egészségügy","mentális egészség","nő","lány","turista","utazás","utazás","busz","autó","szállítás","boldog","utazás","utazás","kaland"],"pt":["podcast","rádio","comunicação social","radiodifusão","mostrar","comunicação","transmissão","podcasting","entretenimento","falar","mental","saúde","saúde mental","mulher","menina","turista","viagens","viajar","autocarro","carro","transporte","feliz","viagem","viagem","aventura"],"pl":["podcast","radio","mediów","nadawanie","pokaż","komunikacja","transmisja","podcasting","rozrywka","mów","psychiczny","zdrowie","zdrowie psychiczne","kobieta","dziewczyna","turystyka","podróże","podróżowanie","autobus","samochód","przewóz","szczęśliwy","podróż","podróż","przygoda"],"nl":["podcast","radio","media","omroep","toon","communicatie","uitzending","verwijdering","amusement","praat","geestelijk","gezondheid","geestelijke gezondheid","vrouw","meisje","toerist","reizen","reizen","bus","voorbeeld","vervoer","blij","reis","reis","avontuur"],"ja":["podcast","ラジオ","メディア","放送","ショー","コミュニケーション","放送","予測すること","エンターテインメント","話を","精神","健康","精神的健康","女性","女の子","観光客","旅行","旅行","バス","車","輸送","ハッピー","旅","旅行","冒険"],"cs":["podcast","rádio","média","vysílání","ukázat","komunikace","vysílání","podcasting","zábava","hovor","duševní","zdraví","duševní zdraví","žena","dívka","turistické","cestování","cestování","autobus","auto","doprava","šťastný","cesta","výlet","dobrodružství"],"tr":["podcast","radyo","ortam","yayın","göster","iletişim","canlı yayın","podcasting","eğlence","konuş","zihinsel","sağlık","ruh sağlığı","kadın","kız","turist","seyahat","seyahat","otobüs","araba","taşıma","mutlu","yolculuk","seyahat","macera"],"uk":["подкаст","радіо","медіа","трансляція","шоу","спілкування","розваги","говорити","психічний","здоров'я","психічне здоров'я","жінка","дівчинка","турист","подорож","подорожі","автобус","кар","транспорт","щаслива","пригода"],"mx":["podcast","radio","medios de comunicación","retransmisión","mostrar","comunicación","difusión","podcaso","entretenimiento","hablar","mental","sanidad","salud mental","mujer","chica","turista","viajes","viajar","autobus","coche","transporte","feliz","viaje","viaje","aventura"]},"industries":["entertainmentLeisure","healthWellness","transportDelivery","travelTourism"],"title":"Podcast Topic Announcement with Happy Woman in Car","localizedTitle":{"en":"Podcast Topic Announcement with Happy Woman in Car","de":"Podcast-Themenankündigung mit glücklicher Frau im Auto","fr":"Annonce de sujet de podcast avec une femme heureuse en voiture","el":"Ανακοίνωση θέματος Podcast με ευτυχισμένη γυναίκα στο αυτοκίνητο","es":"Anuncio de tema de podcast con mujer feliz en coche","ru":"Объявление темы подкаста со счастливой женщиной в машине","it":"Annuncio argomento podcast con donna felice in auto","hu":"Podcast téma bejelentése boldog nővel az autóban","pt":"Anúncio de tópico de podcast com mulher feliz no carro","pl":"Ogłoszenie tematu podcastu z szczęśliwą kobietą w samochodzie","nl":"Podcast-onderwerpaankondiging met gelukkige vrouw in auto","ja":"車の中で幸せな女性とポッドキャストトピックの発表","cs":"Podcast téma oznámení s šťastná žena v autě","tr":"Arabada mutlu bir kadınla podcast konu duyurusu","uk":"Оголошення теми подкасту з щасливою жінкою в автомобілі","mx":"Anuncio de tema de podcast con mujer feliz en coche"},"forSubscribers":true,"v2":true,"language":"en","seoMeta":{"shouldIndex":true}}