{"id":"618b6d75079dcd9363238598","_id":"618b6d75079dcd9363238598","width":1280,"height":720,"categoryCaption":"all","group":"HC","measureUnits":"px","removed":false,"template":[{"animationMode":"elements","customAnimationDuration":0,"elements":[{"top":0,"left":0,"width":1280,"height":720,"angle":0,"uuid":"6DzSDhLqlW8LOnjvBkuy938paBUCyfsro1RZ98NMqP4epDRLdK4b9Mce55vLIt0I","opacity":1,"isBackground":true,"type":"coloredBackground","locked":false,"colors":[{"id":0,"color":"#1812FF"}],"position":{"left":0,"top":0}},{"top":128.82016182763806,"left":380.7171335768154,"width":807.7254694100675,"height":313.2767007525028,"angle":0,"uuid":"mS7c8JLEJqGU5ecN45hF7F2G9eGkgvlqZ0xXyW5N0LyzkFTeQazjNWzJLLGZAWix","mediaId":"6103cad18070ea8a9bd99794","opacity":1,"flipHorizontal":1,"flipVertical":1,"type":"svgElement","locked":false,"colors":[{"id":0,"color":"#000"}],"position":{"left":380.7171335768154,"top":128.82016182763806}},{"top":438.4196886250845,"left":81.13402340991514,"width":280.580301547815,"height":168.53338244786238,"angle":0,"uuid":"w7QcnitsVVWQ36u0nIBr5I47z38Nns6NzJwE5b9k7RpVtv1dm97fJ8v99tWEiaJl","mediaId":"6103cad18070ea8a9bd997db","opacity":1,"flipHorizontal":1,"flipVertical":1,"type":"svgElement","locked":false,"colors":[{"id":0,"color":"#FFF"}],"position":{"left":81.13402340991514,"top":438.4196886250845}},{"top":157.75736711802972,"left":410.91247822765934,"width":751.1091981897358,"height":264.2092656948822,"angle":0,"uuid":"MvXRFKPUb63kOJ00uL4AUUwvINm7lpviwP3rWGkixDXdT0vkKB1oCsAgr9yS3ViS","mediaId":"6103cad18070ea8a9bd99668","opacity":1,"flipHorizontal":1,"flipVertical":1,"type":"maskElement","locked":false,"dphId":"31318455","filters":{"brightness":0,"contrast":0,"saturate":0,"tint":0,"blur":0,"crossProcess":0,"vignette":0},"filtersIntensityEnabled":false,"filtersPresetIntensity":50,"elements":[{"type":"imageElement","uuid":"MvXRFKPUb63kOJ00uL4AUUwvINm7lpviwP3rWGkixDXdT0vkKB1oCsAgr9yS3ViS-sticked","left":-2746.518223866319,"top":-1093.3231042326292,"width":4888.29918273787,"height":3262.4056872259835,"opacity":1,"angle":0,"flipHorizontal":1,"flipVertical":1,"originalImageWidth":4888.299182737869,"originalImageHeight":3262.405687225982,"cropOpts":{"left":0,"top":0,"width":4888.29918273787,"height":3262.4056872259835},"filters":{"brightness":0,"contrast":0,"saturate":0,"tint":0,"blur":0,"crossProcess":0,"vignette":0},"filtersIntensityEnabled":false,"filtersPresetIntensity":50,"mediaId":"6103cad18070ea8a9bd99a17","locked":false,"position":{"left":-2746.518223866319,"top":-1093.3231042326292}}],"maskType":"svg","maskData":{"dimensions":{"width":597,"height":210,"left":166,"top":468}},"colors":[{"id":0,"color":"none"}],"position":{"left":410.91247822765934,"top":157.75736711802972}},{"top":442.12371900855425,"left":93.17212215619065,"width":259.2821268428656,"height":156.49528370158657,"angle":0,"uuid":"TibqHCrRUjMPHjQLqxnR7Jq7NHuwjhWbC67J5DfF7XC1HZGQmGINliJmdgIFBV3u","mediaId":"6103cad18070ea8a9bd99676","opacity":1,"flipHorizontal":1,"flipVertical":1,"type":"maskElement","locked":false,"dphId":"472732880","filters":{"brightness":0,"contrast":0,"saturate":0,"tint":0,"blur":0,"crossProcess":0,"vignette":0},"filtersIntensityEnabled":false,"filtersPresetIntensity":50,"elements":[{"type":"imageElement","uuid":"TibqHCrRUjMPHjQLqxnR7Jq7NHuwjhWbC67J5DfF7XC1HZGQmGINliJmdgIFBV3u-sticked","left":-896.3753527996198,"top":-673.2075221955826,"width":1447.3498723407079,"height":1447.3498723407083,"opacity":1,"angle":0,"flipHorizontal":1,"flipVertical":1,"originalImageWidth":1447.3498723407076,"originalImageHeight":1447.3498723407076,"cropOpts":{"left":0,"top":0,"width":1447.3498723407079,"height":1447.3498723407083},"filters":{"brightness":0,"contrast":0,"saturate":0,"tint":0,"blur":0,"crossProcess":0,"vignette":0},"filtersIntensityEnabled":false,"filtersPresetIntensity":50,"mediaId":"6103cad18070ea8a9bd99970","locked":false,"position":{"left":-896.3753527996198,"top":-673.2075221955826}}],"maskType":"svg","maskData":{"dimensions":{"width":280,"height":169,"left":466,"top":175}},"colors":[{"id":0,"color":"none"}],"position":{"left":93.17212215619065,"top":442.12371900855425}},{"top":113.04692892705322,"left":116.73674143295872,"width":219.46380022056746,"height":233.35391415857856,"angle":0,"uuid":"jECXTmVW0SJWsmyaOOnncY9XsDib7SPLIMy06s6H6OVckzLGe4JtCY1MSZqmP3Pj","mediaId":"6103cad18070ea8a9bd9966e","opacity":1,"flipHorizontal":1,"flipVertical":1,"type":"maskElement","locked":false,"dphId":"472732880","filters":{"brightness":0,"contrast":0,"saturate":0,"tint":0,"blur":0,"crossProcess":0,"vignette":0},"filtersIntensityEnabled":false,"filtersPresetIntensity":50,"elements":[{"type":"imageElement","uuid":"jECXTmVW0SJWsmyaOOnncY9XsDib7SPLIMy06s6H6OVckzLGe4JtCY1MSZqmP3Pj-sticked","left":-347.2528484502659,"top":-450.9656991874117,"width":923.9703791564671,"height":923.9703791564672,"opacity":1,"angle":0,"flipHorizontal":1,"flipVertical":1,"originalImageWidth":923.9703791564672,"originalImageHeight":923.9703791564672,"cropOpts":{"left":0,"top":0,"width":923.9703791564671,"height":923.9703791564672},"filters":{"brightness":0,"contrast":0,"saturate":0,"tint":0,"blur":0,"crossProcess":0,"vignette":0},"filtersIntensityEnabled":false,"filtersPresetIntensity":50,"mediaId":"6103cad18070ea8a9bd99972","locked":false,"position":{"left":-347.2528484502659,"top":-450.9656991874117}}],"maskType":"svg","maskData":{"dimensions":{"width":237,"height":252,"left":161,"top":109}},"colors":[{"id":0,"color":"none"}],"position":{"left":116.73674143295872,"top":113.04692892705322}},{"top":349.6317536222821,"left":29.63008483375677,"width":315.1380089630923,"height":74.33487919062986,"angle":0,"uuid":"wVkqP4V9pj1NIspKh9JjB3w6seznZuN2TXvLOP6oOQnQS1j26I6NIuKNGTggHDhJ","mediaId":"6103cad18070ea8a9bd99828","opacity":1,"flipHorizontal":1,"flipVertical":1,"type":"svgElement","locked":false,"colors":[{"id":0,"color":"#FFF"}],"position":{"left":29.63008483375677,"top":349.6317536222821}},{"top":377,"left":40,"width":340,"height":20,"angle":0.1,"uuid":"tUYaB7wElyXf1kWqIZy8b4cp8mpafm5EJ1ZAjTUzMWwmpvg739y2ffJXlworSSi3","opacity":1,"type":"textElement","locked":false,"fontSize":20,"font":"Daruma Drop One","lineHeight":1,"colorMap":[{"startIndex":0,"endIndex":22,"type":"color","value":"000000"}],"boldMap":[{"startIndex":0,"endIndex":22,"type":"bold","value":false}],"italicMap":[{"startIndex":0,"endIndex":22,"type":"italic","value":false}],"textAlign":"left","capitalize":false,"letterSpacing":0,"text":"EVERYONE TALKS ABOUT IT","wordBreak":"breakWord","underline":false,"lineMap":[{"startIndex":0,"endIndex":22,"value":"line","type":"line"}],"opacityMap":[{"startIndex":0,"endIndex":22,"type":"opacity","value":1}],"underlineMap":[{"startIndex":0,"endIndex":22,"type":"underline","value":false}],"linkMap":[{"startIndex":0,"endIndex":22,"type":"link","value":""}],"position":{"left":40,"top":377}},{"top":215.83377206833217,"left":110.25468826188657,"width":174.08942802306686,"height":94.45277477847202,"angle":0,"uuid":"iQE5YoWXE5PMVLUvoE5cSos6XSjHcZBQtpKzlhM4WJnZ4RzArOo63v2QSTA4pVct","mediaId":"6103cad18070ea8a9bd99700","opacity":1,"flipHorizontal":1,"flipVertical":1,"type":"svgElement","locked":false,"colors":[{"id":0,"color":"#FFF"}],"position":{"left":110.25468826188657,"top":215.83377206833217}},{"top":224.16784043113825,"left":103.77263509081519,"width":174.08942802306663,"height":55.5604557520427,"angle":6.05,"uuid":"CyqUk6R81eriXADoy85ruiw6pvgANHP5v8H3ywuonOJvgn6WIIpIfMe5ZlS62mxn","opacity":1,"type":"textElement","locked":false,"fontSize":52,"font":"Daruma Drop One","lineHeight":1,"colorMap":[{"startIndex":0,"endIndex":4,"type":"color","value":"1812FF"}],"boldMap":[{"startIndex":0,"endIndex":4,"type":"bold","value":false}],"italicMap":[{"startIndex":0,"endIndex":4,"type":"italic","value":false}],"textAlign":"center","capitalize":false,"letterSpacing":0,"text":"sales","wordBreak":"breakWord","underline":false,"lineMap":[{"startIndex":0,"endIndex":4,"value":"line","type":"line"}],"opacityMap":[{"startIndex":0,"endIndex":4,"type":"opacity","value":1}],"position":{"left":103.77263509081519,"top":224.16784043113825}},{"top":210.4932938844613,"left":59.969769306582535,"width":50.284918955303596,"height":88.59723815934456,"angle":0,"uuid":"UL9ZUiPgoLJdGi0MdZ7Ii7Yap7s0RK3MckIz3QzaoT9gYvhfZIegYq3kwAqXEfFW","mediaId":"6103cad18070ea8a9bd9981e","opacity":1,"flipHorizontal":1,"flipVertical":1,"type":"svgElement","locked":false,"colors":[{"id":0,"color":"#FFF"}],"position":{"left":59.969769306582535,"top":210.4932938844613}},{"top":483,"left":427,"width":824,"height":48,"angle":6.23,"uuid":"QKnVtVrF2Ofjwm9DhcuyWhZ21zNKLQs1PInpkkAzhU4a03H82zGtCud4MiStI1tC","opacity":1,"type":"textElement","locked":false,"fontSize":48,"font":"Daruma Drop One","lineHeight":1,"colorMap":[{"startIndex":0,"endIndex":28,"type":"color","value":"FFFFFF"}],"boldMap":[{"startIndex":0,"endIndex":28,"type":"bold","value":false}],"italicMap":[{"startIndex":0,"endIndex":28,"type":"italic","value":false}],"textAlign":"left","capitalize":false,"letterSpacing":0,"text":"COME AND CHECK WITH YOUR EYES","wordBreak":"breakWord","underline":false,"lineMap":[{"startIndex":0,"endIndex":28,"value":"line","type":"line"}],"opacityMap":[{"startIndex":0,"endIndex":28,"type":"opacity","value":1}],"underlineMap":[{"startIndex":0,"endIndex":28,"type":"underline","value":false}],"linkMap":[{"startIndex":0,"endIndex":28,"type":"link","value":""}],"position":{"left":427,"top":483}},{"top":452.5251675166569,"left":945.5664973054874,"width":258.147242574444,"height":105.7470632232662,"angle":0,"uuid":"7lya2Oi2Fc6Ia5ywUTpV2fhJGn0BWuynEIqfs00MNeHr1Dhib2z90BuSzTCbiqZZ","mediaId":"6103cad18070ea8a9bd997dd","opacity":1,"flipHorizontal":1,"flipVertical":1,"type":"svgElement","locked":false,"colors":[{"id":0,"color":"#FFF"}],"position":{"left":945.5664973054874,"top":452.5251675166569}},{"top":360.3868331564424,"left":1203.7137398799314,"width":37.0849214108398,"height":78.03285546864214,"angle":0,"uuid":"n3YRL2b759eHoppLhEDT2P3THI3CmBi8IRwSv64PZDykdH1KZPlIjNTtKmgmFYIP","mediaId":"6103cad18070ea8a9bd997c8","opacity":1,"flipHorizontal":1,"flipVertical":-1,"type":"svgElement","locked":false,"colors":[{"id":0,"color":"#FFF"}],"position":{"left":1203.7137398799314,"top":360.3868331564424}}],"uuid":"iMRx2Oydr8CdN1wbLdv95vp1y6Tz6XpQtR5o05cSS82nWMsFi9aC7xbzRhvdR0iO","audio":[]}],"templateType":"regular","hash":"618b6be0047b4813ab70d398","pixelWidth":1280,"pixelHeight":720,"previewImageUrls":["/downloads/6dd28c08-2969-4929-a35c-0d3dc1d53e67.jpeg"],"hasAnimatedPreview":false,"hasAnimatedScreenPreview":false,"previewPending":false,"previewUpdatedAt":"2021-11-10T06:58:41.134Z","status":"completed","format":"Youtube Thumbnail","suitability":["mobile"],"studioName":"Crello","createdAt":1636527477917,"updatedAt":1636630231896,"acceptedAt":1636630231896,"attributedAt":1636630231207,"keywords":{"en":["funny","lips","illustration","face","cute","girl","fun","eyes","mouth","smile","character","comic","female","male","arrow","sticker","humor","humorous","crazy","sale","black friday","blackfriday","dizzy","youtube","cover"],"de":["lippen","gesicht","mädchen","spaß","augen","zeichen","pfeil","bis sale"],"fr":["lèvres","visage","fille","yeux","bouche","sourire","personnage","fléche","autocollant","humour","a vendre"],"el":["βελακι"],"es":["gracioso","labios","ilustración","rostro","niña mirando","divertida","ojos","boca","sonris","cómic","varon","flechaz","calcomania","loca","venta","postee"],"ru":["веселый","губ","иллюстрация","рожица","девушк","веселье","глаза","рот","улыбкаъ","персонаж","женские","мужской","вниз  стрелка","наклейка","юмор","в продаже","чёрная пятница","новый пост"],"it":["bocca","freccia","vendita"],"hu":["arca","sem fun","nyíl"],"pt":["engracado","lábios","rosto","fofos","menina logo","diversão","olhos","sorriso","personagem","femininos","masc","seta baixo","humorado","louca","liquidação","para facebook","postar"],"pl":["twarz","baw sie dobrz","oczy","uśmiech","bohater","strzałka w dół","naklejka","wyprzedaż","poczta"],"nl":["meisje","mond","pijl","plakkertje"],"ja":["やじるし"],"cs":["úsměv","šipka"],"tr":["dudak","illüstrasyon","kız","ağız","gülücük","ok işareti","çıkartma"],"uk":["обличчя","дівчина","очі","сміжка","cтрілка","стікер","допис","знижки"],"mx":["gracioso","labios","ilustración","rostro","niña mirando","divertida","ojos","boca","sonris","cómic","varon","flechaz","calcomania","loca","venta","postee"]},"industries":["artCrafts","beautyCosmetics","entertainmentLeisure","fashionStyle","homeLiving","retail"],"title":"Sale Announcement with Funny Lips and Eyes","localizedTitle":{"en":"Sale Announcement with Funny Lips and Eyes","de":"Verkaufsankündigung mit lustigen Lippen und Augen","fr":"Annonce de vente avec des lèvres et des yeux drôles","el":"Ανακοίνωση πώλησης με αστεία χείλη και μάτια","es":"Anuncio de venta con ojos y labios divertidos","ru":"Объявление о распродаже с забавными губами и глазами","it":"Annuncio di vendita con labbra e occhi divertenti","hu":"Eladó hirdetmény vicces ajkakkal és szemekkel","pt":"Anúncio de venda com lábios e olhos engraçados","pl":"Ogłoszenie sprzedaży z zabawnymi ustami i oczami","nl":"Verkoopaankondiging met grappige lippen en ogen","ja":"面白い唇と目での販売発表","cs":"Oznámení o prodeji s legračními rty a očima","tr":"Komik dudaklar ve gözler ile satış duyurusu","uk":"Оголошення про продаж зі смішними губами та очима","mx":"Anuncio de venta con ojos y labios divertidos"},"forSubscribers":true,"v2":true,"language":"en","seoMeta":{"shouldIndex":true}}