{"id":"62f4f28bca4d77aa72a955d7","width":360,"height":504,"path":"background.jpeg","matrix":"1.8253968,0.0,55.0,0.0,1.8253968,0.0,0.0,0.0,1.0","sticker":[{"type":"drawable","path":"drawable0.png","matrix":"0.6449756,0.0,39.47694,0.0,0.6451207,-56.09656,0.0,0.0,1.0","color_fill":0,"isLock":false},{"type":"drawable","path":"drawable1.png","matrix":"0.11871284,0.0,509.79767,0.0,0.11871284,706.2046,0.0,0.0,1.0","color_fill":-29952,"isLock":false},{"type":"drawable","path":"drawable2.png","matrix":"0.10282303,0.0,101.32446,0.0,0.10282303,50.525566,0.0,0.0,1.0","color_fill":-29952,"isLock":false},{"type":"text","matrix":"1.8253968,0.0,180.764,0.0,1.8253968,314.65778,0.0,0.0,1.0","content":"CARVING","sizePx":46,"fontPosition":-1,"fontName":"Milonga","alignment":2,"isLower":true,"isBold":false,"isUnderline":false,"isItalic":false,"spacing":0,"lineHeight":20,"textOpacity":255,"colorShadow":0,"blurShadow":80,"offsetX":10,"offsetY":5,"shadowPosition":0,"borderPosition":0,"colorBorder":0,"sizeBorder":5,"backgroundOpacity":255,"paddingBackgroundX":0,"paddingBackgroundY":0,"roundBackground":0,"curve":0,"gradientPosition":0,"angleGradientText":0,"palettePosition":0,"colorText":-16777216,"colorPosition":0,"colorBackgroundPosition":0,"colorBackground":0,"gradientBackgroundPosition":0,"angleGradientBackground":90,"colorBorderBackground":0,"colorBorderBackgroundPosition":0,"borderBackgroundOpacity":255,"sizeBorderBackground":3,"isLock":false},{"type":"text","matrix":"1.8253968,0.0,283.67523,0.0,1.8253968,190.61938,0.0,0.0,1.0","content":"HALLOWEEN","sizePx":17,"fontPosition":-1,"fontName":"Milonga","alignment":2,"isLower":true,"isBold":false,"isUnderline":false,"isItalic":false,"spacing":0,"lineHeight":20,"textOpacity":255,"colorShadow":0,"blurShadow":80,"offsetX":10,"offsetY":5,"shadowPosition":0,"borderPosition":0,"colorBorder":0,"sizeBorder":5,"backgroundOpacity":255,"paddingBackgroundX":0,"paddingBackgroundY":0,"roundBackground":0,"curve":0,"gradientPosition":0,"angleGradientText":0,"palettePosition":0,"colorText":-16777216,"colorPosition":0,"colorBackgroundPosition":0,"colorBackground":0,"gradientBackgroundPosition":0,"angleGradientBackground":90,"colorBorderBackground":0,"colorBorderBackgroundPosition":0,"borderBackgroundOpacity":255,"sizeBorderBackground":3,"isLock":false},{"type":"text","matrix":"1.8253968,0.0,302.93768,0.0,1.8253968,85.83271,0.0,0.0,1.0","content":"INVITATION","sizePx":11,"fontPosition":-1,"fontName":"Trirong","alignment":2,"isLower":true,"isBold":false,"isUnderline":false,"isItalic":false,"spacing":0.2160000056028366,"lineHeight":20,"textOpacity":255,"colorShadow":0,"blurShadow":80,"offsetX":10,"offsetY":5,"shadowPosition":0,"borderPosition":0,"colorBorder":0,"sizeBorder":5,"backgroundOpacity":255,"paddingBackgroundX":0,"paddingBackgroundY":0,"roundBackground":0,"curve":0,"gradientPosition":0,"angleGradientText":0,"palettePosition":0,"colorText":-16777216,"colorPosition":0,"colorBackgroundPosition":0,"colorBackground":0,"gradientBackgroundPosition":0,"angleGradientBackground":90,"colorBorderBackground":0,"colorBorderBackgroundPosition":0,"borderBackgroundOpacity":255,"sizeBorderBackground":3,"isLock":false},{"type":"text","matrix":"1.8253968,0.0,181.99057,0.0,1.8253968,244.76996,0.0,0.0,1.0","content":"PUPMKIN","sizePx":43,"fontPosition":-1,"fontName":"Milonga","alignment":2,"isLower":true,"isBold":false,"isUnderline":false,"isItalic":false,"spacing":0,"lineHeight":20,"textOpacity":255,"colorShadow":0,"blurShadow":80,"offsetX":10,"offsetY":5,"shadowPosition":0,"borderPosition":0,"colorBorder":0,"sizeBorder":5,"backgroundOpacity":255,"paddingBackgroundX":0,"paddingBackgroundY":0,"roundBackground":0,"curve":0,"gradientPosition":0,"angleGradientText":0,"palettePosition":0,"colorText":-16777216,"colorPosition":0,"colorBackgroundPosition":0,"colorBackground":0,"gradientBackgroundPosition":0,"angleGradientBackground":90,"colorBorderBackground":0,"colorBorderBackgroundPosition":0,"borderBackgroundOpacity":255,"sizeBorderBackground":3,"isLock":false},{"type":"text","matrix":"1.8253968,0.0,135.54378,0.0,1.8253968,85.773224,0.0,0.0,1.0","content":"OCT\n29","sizePx":11,"fontPosition":-1,"fontName":"Trirong","alignment":2,"isLower":true,"isBold":true,"isUnderline":false,"isItalic":false,"spacing":0,"lineHeight":6.399999618530273,"textOpacity":255,"colorShadow":0,"blurShadow":80,"offsetX":10,"offsetY":5,"shadowPosition":0,"borderPosition":0,"colorBorder":0,"sizeBorder":5,"backgroundOpacity":255,"paddingBackgroundX":0,"paddingBackgroundY":0,"roundBackground":0,"curve":0,"gradientPosition":0,"angleGradientText":0,"palettePosition":0,"colorText":-1,"colorPosition":1,"colorBackgroundPosition":0,"colorBackground":0,"gradientBackgroundPosition":0,"angleGradientBackground":90,"colorBorderBackground":0,"colorBorderBackgroundPosition":0,"borderBackgroundOpacity":255,"sizeBorderBackground":3,"isLock":false},{"type":"text","matrix":"1.6373829,0.0,549.27716,0.0,1.6373829,738.8568,0.0,0.0,1.0","content":"$5","sizePx":24,"fontPosition":-1,"fontName":"Milonga","alignment":2,"isLower":true,"isBold":false,"isUnderline":false,"isItalic":false,"spacing":0,"lineHeight":20,"textOpacity":255,"colorShadow":0,"blurShadow":80,"offsetX":10,"offsetY":5,"shadowPosition":0,"borderPosition":0,"colorBorder":0,"sizeBorder":5,"backgroundOpacity":255,"paddingBackgroundX":0,"paddingBackgroundY":0,"roundBackground":0,"curve":0,"gradientPosition":0,"angleGradientText":0,"palettePosition":0,"colorText":-1,"colorPosition":1,"colorBackgroundPosition":0,"colorBackground":0,"gradientBackgroundPosition":0,"angleGradientBackground":90,"colorBorderBackground":0,"colorBorderBackgroundPosition":0,"borderBackgroundOpacity":255,"sizeBorderBackground":3,"isLock":false},{"type":"text","matrix":"1.9068109,0.0,547.86096,0.0,1.9068109,786.86755,0.0,0.0,1.0","content":"ENTRY","sizePx":8,"fontPosition":-1,"fontName":"Trirong","alignment":2,"isLower":true,"isBold":true,"isUnderline":false,"isItalic":false,"spacing":0,"lineHeight":20,"textOpacity":255,"colorShadow":0,"blurShadow":80,"offsetX":10,"offsetY":5,"shadowPosition":0,"borderPosition":0,"colorBorder":0,"sizeBorder":5,"backgroundOpacity":255,"paddingBackgroundX":0,"paddingBackgroundY":0,"roundBackground":0,"curve":0,"gradientPosition":0,"angleGradientText":0,"palettePosition":0,"colorText":-1,"colorPosition":1,"colorBackgroundPosition":0,"colorBackground":0,"gradientBackgroundPosition":0,"angleGradientBackground":90,"colorBorderBackground":0,"colorBorderBackgroundPosition":0,"borderBackgroundOpacity":255,"sizeBorderBackground":3,"isLock":false},{"type":"drawable","path":"drawable10.png","matrix":"1.8280411,0.0,147.73016,0.0,1.8280411,739.35626,0.0,0.0,1.0","color_fill":-1,"isLock":false},{"type":"text","matrix":"1.8253968,0.0,571.2063,0.0,1.8253968,85.817085,0.0,0.0,1.0","content":"3 PM","sizePx":11,"fontPosition":-1,"fontName":"Trirong","alignment":2,"isLower":true,"isBold":true,"isUnderline":false,"isItalic":false,"spacing":0,"lineHeight":20,"textOpacity":255,"colorShadow":0,"blurShadow":80,"offsetX":10,"offsetY":5,"shadowPosition":0,"borderPosition":0,"colorBorder":0,"sizeBorder":5,"backgroundOpacity":255,"paddingBackgroundX":0,"paddingBackgroundY":0,"roundBackground":0,"curve":0,"gradientPosition":0,"angleGradientText":0,"palettePosition":0,"colorText":-16777216,"colorPosition":0,"colorBackgroundPosition":0,"colorBackground":0,"gradientBackgroundPosition":0,"angleGradientBackground":90,"colorBorderBackground":0,"colorBorderBackgroundPosition":0,"borderBackgroundOpacity":255,"sizeBorderBackground":3,"isLock":false},{"type":"drawable","path":"drawable12.png","matrix":"0.08893506,0.0,155.46078,0.0,0.089034654,747.13135,0.0,0.0,1.0","color_fill":0,"isLock":false},{"type":"drawable","path":"drawable13.png","matrix":"0.09514281,0.045077078,588.03577,-0.045077078,0.09514281,-8.007976,0.0,0.0,1.0","color_fill":0,"isLock":false},{"type":"drawable","path":"drawable14.png","matrix":"0.8893194,0.0,161.24156,0.0,0.8893194,411.8,0.0,0.0,1.0","color_fill":-16777216,"isLock":false}],"ext":{"en":["halloween","holiday","celebration","orange","decoration","carving","event","invitation"]}}