{"id":"63235addd924097ccfc09684","width":360,"height":504,"path":"background.jpeg","matrix":"3.0,0.0,0.0,0.0,3.0,121.0,0.0,0.0,1.0","sticker":[{"type":"drawable","path":"drawable1664079223422.png","matrix":"0.0,1.2282934,-164.66716,-1.2284935,0.0,1743.4886,0.0,0.0,1.0","color_fill":0,"isLock":false},{"type":"drawable","path":"drawable1664079223513.png","matrix":"0.3201394,0.040969115,157.53767,-0.040969115,0.3201394,834.141,0.0,0.0,1.0","color_fill":-8090261,"isLock":false},{"type":"text","matrix":"3.0,0.0,309.56427,0.0,3.0,390.03687,0.0,0.0,1.0","content":"Decorate your very own wreath for \nyour front door with our online","sizePx":9,"fontPosition":-1,"fontName":"Tenor Sans","alignment":2,"isLower":true,"isBold":false,"isUnderline":false,"isItalic":false,"spacing":0.008000001311302185,"lineHeight":5.200000762939453,"textOpacity":255,"colorShadow":0,"blurShadow":80,"offsetX":10,"offsetY":5,"shadowPosition":0,"borderPosition":0,"colorBorder":0,"sizeBorder":5,"backgroundOpacity":255,"paddingBackgroundX":0,"paddingBackgroundY":0,"roundBackground":0,"curve":0,"gradientPosition":0,"angleGradientText":0,"palettePosition":0,"colorText":-16777216,"colorPosition":0,"colorBackgroundPosition":0,"colorBackground":0,"gradientBackgroundPosition":0,"angleGradientBackground":90,"colorBorderBackground":0,"colorBorderBackgroundPosition":0,"borderBackgroundOpacity":255,"sizeBorderBackground":3,"isLock":false},{"type":"text","matrix":"3.0,0.0,176.96954,0.0,3.0,538.26514,0.0,0.0,1.0","content":"Christmas\nWreath Making","sizePx":29,"fontPosition":-1,"fontName":"FoglihtenNo06","alignment":2,"isLower":true,"isBold":false,"isUnderline":false,"isItalic":false,"spacing":0,"lineHeight":11.200000762939453,"textOpacity":255,"colorShadow":0,"blurShadow":80,"offsetX":10,"offsetY":5,"shadowPosition":0,"borderPosition":0,"colorBorder":0,"sizeBorder":5,"backgroundOpacity":255,"paddingBackgroundX":0,"paddingBackgroundY":0,"roundBackground":0,"curve":0,"gradientPosition":0,"angleGradientText":0,"palettePosition":0,"colorText":-4366513,"colorPosition":0,"colorBackgroundPosition":0,"colorBackground":0,"gradientBackgroundPosition":0,"angleGradientBackground":90,"colorBorderBackground":0,"colorBorderBackgroundPosition":0,"borderBackgroundOpacity":255,"sizeBorderBackground":3,"isLock":false},{"type":"text","matrix":"2.975732,0.38081297,196.65785,-0.38081297,2.975732,874.0261,0.0,0.0,1.0","content":"Workshop","sizePx":17,"fontPosition":-1,"fontName":"FoglihtenNo06","alignment":2,"isLower":true,"isBold":false,"isUnderline":false,"isItalic":false,"spacing":0,"lineHeight":20,"textOpacity":255,"colorShadow":0,"blurShadow":80,"offsetX":10,"offsetY":5,"shadowPosition":0,"borderPosition":0,"colorBorder":0,"sizeBorder":5,"backgroundOpacity":255,"paddingBackgroundX":0,"paddingBackgroundY":0,"roundBackground":0,"curve":0,"gradientPosition":0,"angleGradientText":0,"palettePosition":0,"colorText":-16777216,"colorPosition":0,"colorBackgroundPosition":0,"colorBackground":0,"gradientBackgroundPosition":0,"angleGradientBackground":90,"colorBorderBackground":0,"colorBorderBackgroundPosition":0,"borderBackgroundOpacity":255,"sizeBorderBackground":3,"isLock":false},{"type":"text","matrix":"3.0,0.0,156.0,0.0,3.0,240.59999,0.0,0.0,1.0","content":"DEC\n03","sizePx":17,"fontPosition":-1,"fontName":"FoglihtenNo06","alignment":1,"isLower":true,"isBold":false,"isUnderline":false,"isItalic":false,"spacing":0,"lineHeight":8.799999237060547,"textOpacity":255,"colorShadow":0,"blurShadow":80,"offsetX":10,"offsetY":5,"shadowPosition":0,"borderPosition":0,"colorBorder":0,"sizeBorder":5,"backgroundOpacity":255,"paddingBackgroundX":0,"paddingBackgroundY":0,"roundBackground":0,"curve":0,"gradientPosition":0,"angleGradientText":0,"palettePosition":0,"colorText":-16777216,"colorPosition":0,"colorBackgroundPosition":0,"colorBackground":0,"gradientBackgroundPosition":0,"angleGradientBackground":90,"colorBorderBackground":0,"colorBorderBackgroundPosition":0,"borderBackgroundOpacity":255,"sizeBorderBackground":3,"isLock":false},{"type":"text","matrix":"3.0,0.0,847.30835,0.0,3.0,248.98402,0.0,0.0,1.0","content":"12\nPM","sizePx":17,"fontPosition":-1,"fontName":"FoglihtenNo06","alignment":3,"isLower":true,"isBold":false,"isUnderline":false,"isItalic":false,"spacing":0.01600000262260437,"lineHeight":7.600000381469727,"textOpacity":255,"colorShadow":0,"blurShadow":80,"offsetX":10,"offsetY":5,"shadowPosition":0,"borderPosition":0,"colorBorder":0,"sizeBorder":5,"backgroundOpacity":255,"paddingBackgroundX":0,"paddingBackgroundY":0,"roundBackground":0,"curve":0,"gradientPosition":0,"angleGradientText":0,"palettePosition":0,"colorText":-16777216,"colorPosition":0,"colorBackgroundPosition":0,"colorBackground":0,"gradientBackgroundPosition":0,"angleGradientBackground":90,"colorBorderBackground":0,"colorBorderBackgroundPosition":0,"borderBackgroundOpacity":255,"sizeBorderBackground":3,"isLock":false},{"type":"drawable","path":"drawable1664079223859.png","matrix":"0.6132481,0.0,246.86742,0.0,0.6132481,-280.33618,0.0,0.0,1.0","color_fill":-8090261,"isLock":false},{"type":"drawable","path":"drawable1664079223887.png","matrix":"3.007136,0.0,463.31805,0.0,3.007136,1325.636,0.0,0.0,1.0","color_fill":-1,"isLock":false},{"type":"text","matrix":"3.0,0.0,554.01685,0.0,3.0,782.6852,0.0,0.0,1.0","content":"You'll get \rthe craft kit \ndelivered to your home with \nall the embellishments, just \nchoose from a frosted \nwreath or classic \rwreath.","sizePx":9,"fontPosition":-1,"fontName":"Tenor Sans","alignment":1,"isLower":true,"isBold":false,"isUnderline":false,"isItalic":false,"spacing":0,"lineHeight":5.200000762939453,"textOpacity":255,"colorShadow":0,"blurShadow":80,"offsetX":10,"offsetY":5,"shadowPosition":0,"borderPosition":0,"colorBorder":0,"sizeBorder":5,"backgroundOpacity":255,"paddingBackgroundX":0,"paddingBackgroundY":0,"roundBackground":0,"curve":0,"gradientPosition":0,"angleGradientText":0,"palettePosition":0,"colorText":-16777216,"colorPosition":0,"colorBackgroundPosition":0,"colorBackground":0,"gradientBackgroundPosition":0,"angleGradientBackground":90,"colorBorderBackground":0,"colorBorderBackgroundPosition":0,"borderBackgroundOpacity":255,"sizeBorderBackground":3,"isLock":false},{"type":"drawable","path":"drawable1664079223887.png","matrix":"0.12659071,0.0,483.94385,0.0,0.12673247,1347.7717,0.0,0.0,1.0","color_fill":0,"isLock":false}],"ext":{"en":["christmas","holiday","decoration","winter","merry","xmas","season","festive","celebration","hellochristmas","event","invitation","workshop","craft","wreath","toys","qr code","handiwork"]}}