{"id":"62ea8614ca4d77aa7285e981","width":360,"height":504,"path":"background.jpeg","matrix":"3.0,0.0,0.0,0.0,3.0,121.0,0.0,0.0,1.0","sticker":[{"opacity":255,"opacity_border":255,"color_border":0,"size_border":20,"type":"drawable","path":"drawable1664138008718.png","matrix":"0.8484658,0.0,65.659966,0.0,0.79651225,710.6421,0.0,0.0,1.0","color_fill":-16777216,"isLock":false,"width":1080,"height":1080},{"opacity":255,"opacity_border":255,"color_border":0,"size_border":20,"type":"drawable","path":"drawable1664138008762.png","matrix":"0.5173795,0.0,164.86841,0.0,0.51052743,692.356,0.0,0.0,1.0","color_fill":0,"isLock":false,"width":1387,"height":1600},{"type":"text","matrix":"3.0,0.0,670.66644,0.0,3.0,609.1321,0.0,0.0,1.0","width":97,"height":23,"content":"IT'S TIME TO DRINK\nBEER AND RELAX","sizePx":11,"fontPosition":-1,"fontName":"Space Grotesk","alignment":3,"isLower":false,"isBold":true,"isUnderline":false,"isItalic":false,"spacing":0.008000001311302185,"lineHeight":6.399999618530273,"textOpacity":255,"colorShadow":0,"blurShadow":80,"offsetX":10,"offsetY":5,"shadowPosition":0,"borderPosition":0,"colorBorder":0,"sizeBorder":5,"backgroundOpacity":255,"paddingBackgroundX":0,"paddingBackgroundY":0,"roundBackground":0,"curve":0,"gradientPosition":0,"angleGradientText":0,"palettePosition":0,"colorText":-1,"colorPosition":1,"colorBackgroundPosition":0,"colorBackground":0,"gradientBackgroundPosition":0,"angleGradientBackground":90,"colorBorderBackground":0,"colorBorderBackgroundPosition":0,"borderBackgroundOpacity":255,"sizeBorderBackground":3,"isLock":false},{"type":"text","matrix":"3.0,0.0,125.12286,0.0,3.0,613.62573,0.0,0.0,1.0","width":89,"height":47,"content":"SEP 17-\nOCT 03","sizePx":27,"fontPosition":-1,"fontName":"Space Grotesk","alignment":1,"isLower":true,"isBold":true,"isUnderline":false,"isItalic":false,"spacing":0,"lineHeight":6.399999618530273,"textOpacity":255,"colorShadow":0,"blurShadow":80,"offsetX":10,"offsetY":5,"shadowPosition":0,"borderPosition":0,"colorBorder":0,"sizeBorder":5,"backgroundOpacity":255,"paddingBackgroundX":0,"paddingBackgroundY":0,"roundBackground":0,"curve":0,"gradientPosition":0,"angleGradientText":0,"palettePosition":0,"colorText":-1,"colorPosition":1,"colorBackgroundPosition":0,"colorBackground":0,"gradientBackgroundPosition":0,"angleGradientBackground":90,"colorBorderBackground":0,"colorBorderBackgroundPosition":0,"borderBackgroundOpacity":255,"sizeBorderBackground":3,"isLock":false},{"type":"text","matrix":"3.0,0.0,96.16156,0.0,3.0,232.35336,0.0,0.0,1.0","width":284,"height":102,"content":"BEER\nFESTIVAL","sizePx":65,"fontPosition":-1,"fontName":"Unlock","alignment":1,"isLower":false,"isBold":false,"isUnderline":false,"isItalic":false,"spacing":0,"lineHeight":16,"textOpacity":255,"colorShadow":0,"blurShadow":80,"offsetX":10,"offsetY":5,"shadowPosition":0,"borderPosition":0,"colorBorder":0,"sizeBorder":5,"backgroundOpacity":255,"paddingBackgroundX":0,"paddingBackgroundY":0,"roundBackground":0,"curve":0,"gradientPosition":0,"angleGradientText":0,"palettePosition":0,"colorText":-1,"colorPosition":1,"colorBackgroundPosition":0,"colorBackground":0,"gradientBackgroundPosition":0,"angleGradientBackground":90,"colorBorderBackground":0,"colorBorderBackgroundPosition":0,"borderBackgroundOpacity":255,"sizeBorderBackground":3,"isLock":false},{"opacity":255,"opacity_border":255,"color_border":0,"size_border":20,"type":"drawable","path":"drawable1664138008949.png","matrix":"0.2059234,0.0,765.8813,0.0,0.2059234,702.73004,0.0,0.0,1.0","color_fill":-2705372,"isLock":false,"width":1053,"height":1080},{"type":"text","matrix":"3.0,0.0,825.6065,0.0,3.0,785.4677,0.0,0.0,1.0","width":31,"height":19,"content":"BRAND\nNAME\n","sizePx":10,"fontPosition":-1,"fontName":"Space Grotesk","alignment":2,"isLower":false,"isBold":true,"isUnderline":false,"isItalic":false,"spacing":0,"lineHeight":5.200000762939453,"textOpacity":255,"colorShadow":0,"blurShadow":80,"offsetX":10,"offsetY":5,"shadowPosition":0,"borderPosition":0,"colorBorder":0,"sizeBorder":5,"backgroundOpacity":255,"paddingBackgroundX":0,"paddingBackgroundY":0,"roundBackground":0,"curve":0,"gradientPosition":0,"angleGradientText":0,"palettePosition":0,"colorText":-16777216,"colorPosition":0,"colorBackgroundPosition":0,"colorBackground":0,"gradientBackgroundPosition":0,"angleGradientBackground":90,"colorBorderBackground":0,"colorBorderBackgroundPosition":0,"borderBackgroundOpacity":255,"sizeBorderBackground":3,"isLock":false},{"type":"text","matrix":"3.0,0.0,249.4979,0.0,3.0,1496.7402,0.0,0.0,1.0","width":192,"height":8,"content":"JOIN THE OKTOBERFEST CELEBRATION\n","sizePx":11,"fontPosition":-1,"fontName":"Space Grotesk","alignment":2,"isLower":false,"isBold":false,"isUnderline":false,"isItalic":false,"spacing":0.008000001311302185,"lineHeight":20,"textOpacity":255,"colorShadow":0,"blurShadow":80,"offsetX":10,"offsetY":5,"shadowPosition":0,"borderPosition":0,"colorBorder":0,"sizeBorder":5,"backgroundOpacity":255,"paddingBackgroundX":0,"paddingBackgroundY":0,"roundBackground":0,"curve":0,"gradientPosition":0,"angleGradientText":0,"palettePosition":0,"colorText":-1,"colorPosition":1,"colorBackgroundPosition":0,"colorBackground":0,"gradientBackgroundPosition":0,"angleGradientBackground":90,"colorBorderBackground":0,"colorBorderBackgroundPosition":0,"borderBackgroundOpacity":255,"sizeBorderBackground":3,"isLock":false}],"ext":{"en":["oktoberfest","beer","german","festival","germany","drink","party","celebration","traditional","fest","october","alcohol","holiday","culture","tradition","fun","glass","bottle","maroon color","funny","red","invitation"]}}