{"id":"62f50179ca4d77aa7251f833","width":360,"height":504,"path":"background.jpeg","matrix":"1.8253968,0.0,55.0,0.0,1.8253968,0.0,0.0,0.0,1.0","sticker":[{"type":"drawable","path":"drawable0.png","matrix":"1.7411618,1.6155045E-8,134.81844,-1.6155045E-8,1.7411618,495.28268,0.0,0.0,1.0","color_fill":-1,"isLock":false},{"type":"text","matrix":"1.8253968,0.0,113.45094,0.0,1.8253968,54.297024,0.0,0.0,1.0","content":"HALLOWEEN\n\nPARTY","sizePx":42,"fontPosition":-1,"fontName":"Bowlby One","alignment":2,"isLower":false,"isBold":false,"isUnderline":false,"isItalic":false,"spacing":0,"lineHeight":10,"textOpacity":255,"colorShadow":0,"blurShadow":80,"offsetX":10,"offsetY":5,"shadowPosition":0,"borderPosition":0,"colorBorder":0,"sizeBorder":5,"backgroundOpacity":255,"paddingBackgroundX":0,"paddingBackgroundY":0,"roundBackground":0,"curve":0,"gradientPosition":0,"angleGradientText":0,"palettePosition":0,"colorText":-16777216,"colorPosition":0,"colorBackgroundPosition":0,"colorBackground":0,"gradientBackgroundPosition":0,"angleGradientBackground":90,"colorBorderBackground":0,"colorBorderBackgroundPosition":0,"borderBackgroundOpacity":255,"sizeBorderBackground":3,"isLock":false},{"type":"text","matrix":"1.8253968,0.0,134.98944,0.0,1.8253968,79.72552,0.0,0.0,1.0","content":"Costume","sizePx":79,"fontPosition":-1,"fontName":"Sedgwick Ave Display","alignment":2,"isLower":true,"isBold":false,"isUnderline":false,"isItalic":false,"spacing":0,"lineHeight":20,"textOpacity":255,"colorShadow":0,"blurShadow":80,"offsetX":10,"offsetY":5,"shadowPosition":0,"borderPosition":0,"colorBorder":0,"sizeBorder":5,"backgroundOpacity":255,"paddingBackgroundX":0,"paddingBackgroundY":0,"roundBackground":0,"curve":0,"gradientPosition":0,"angleGradientText":0,"palettePosition":0,"colorText":-15006813,"colorPosition":0,"colorBackgroundPosition":0,"colorBackground":0,"gradientBackgroundPosition":0,"angleGradientBackground":90,"colorBorderBackground":0,"colorBorderBackgroundPosition":0,"borderBackgroundOpacity":255,"sizeBorderBackground":3,"isLock":false},{"type":"drawable","path":"drawable3.png","matrix":"0.4470741,0.0,145.0574,0.0,0.41953987,472.35095,0.0,0.0,1.0","color_fill":0,"isLock":false},{"type":"drawable","path":"drawable4.png","matrix":"1.8300663,0.0,175.73573,0.0,1.8389183,337.62457,0.0,0.0,1.0","color_fill":-1,"isLock":false},{"type":"drawable","path":"drawable5.png","matrix":"1.8571165,0.0,549.6077,0.0,1.8571165,495.20084,0.0,0.0,1.0","color_fill":-41215,"isLock":false},{"type":"drawable","path":"drawable6.png","matrix":"0.07522405,0.0,142.07297,0.0,0.07530829,502.57483,0.0,0.0,1.0","color_fill":0,"isLock":false},{"type":"text","matrix":"1.8253968,0.0,566.4621,0.0,1.8253968,507.8113,0.0,0.0,1.0","content":"31\n","sizePx":19,"fontPosition":-1,"fontName":"Bowlby One","alignment":2,"isLower":true,"isBold":false,"isUnderline":false,"isItalic":false,"spacing":0,"lineHeight":20,"textOpacity":255,"colorShadow":0,"blurShadow":80,"offsetX":10,"offsetY":5,"shadowPosition":0,"borderPosition":0,"colorBorder":0,"sizeBorder":5,"backgroundOpacity":255,"paddingBackgroundX":0,"paddingBackgroundY":0,"roundBackground":0,"curve":0,"gradientPosition":0,"angleGradientText":0,"palettePosition":0,"colorText":-16777216,"colorPosition":0,"colorBackgroundPosition":0,"colorBackground":0,"gradientBackgroundPosition":0,"angleGradientBackground":90,"colorBorderBackground":0,"colorBorderBackgroundPosition":0,"borderBackgroundOpacity":255,"sizeBorderBackground":3,"isLock":false},{"type":"drawable","path":"drawable8.png","matrix":"1.8571165,0.0,553.8516,0.0,1.8571165,582.4853,0.0,0.0,1.0","color_fill":-1,"isLock":false},{"type":"text","matrix":"1.8253968,0.0,566.4621,0.0,1.8253968,542.49384,0.0,0.0,1.0","content":"oct","sizePx":15,"fontPosition":-1,"fontName":"Bowlby One","alignment":2,"isLower":true,"isBold":false,"isUnderline":false,"isItalic":false,"spacing":0,"lineHeight":20,"textOpacity":255,"colorShadow":0,"blurShadow":80,"offsetX":10,"offsetY":5,"shadowPosition":0,"borderPosition":0,"colorBorder":0,"sizeBorder":5,"backgroundOpacity":255,"paddingBackgroundX":0,"paddingBackgroundY":0,"roundBackground":0,"curve":0,"gradientPosition":0,"angleGradientText":0,"palettePosition":0,"colorText":-16777216,"colorPosition":0,"colorBackgroundPosition":0,"colorBackground":0,"gradientBackgroundPosition":0,"angleGradientBackground":90,"colorBorderBackground":0,"colorBorderBackgroundPosition":0,"borderBackgroundOpacity":255,"sizeBorderBackground":3,"isLock":false},{"type":"text","matrix":"1.8253968,0.0,568.4936,0.0,1.8253968,597.48895,0.0,0.0,1.0","content":"7 PM\n—\n1AM","sizePx":11,"fontPosition":-1,"fontName":"Bowlby One","alignment":2,"isLower":true,"isBold":false,"isUnderline":false,"isItalic":false,"spacing":0,"lineHeight":2.799999237060547,"textOpacity":255,"colorShadow":0,"blurShadow":80,"offsetX":10,"offsetY":5,"shadowPosition":0,"borderPosition":0,"colorBorder":0,"sizeBorder":5,"backgroundOpacity":255,"paddingBackgroundX":0,"paddingBackgroundY":0,"roundBackground":0,"curve":0,"gradientPosition":0,"angleGradientText":0,"palettePosition":0,"colorText":-15006813,"colorPosition":0,"colorBackgroundPosition":0,"colorBackground":0,"gradientBackgroundPosition":0,"angleGradientBackground":90,"colorBorderBackground":0,"colorBorderBackgroundPosition":0,"borderBackgroundOpacity":255,"sizeBorderBackground":3,"isLock":false},{"type":"drawable","path":"drawable11.png","matrix":"1.7458407,0.0,184.82211,0.0,1.7542852,339.9343,0.0,0.0,1.0","color_fill":-41215,"isLock":false},{"type":"text","matrix":"1.9830374,0.0,250.6081,0.0,1.9830374,378.03058,0.0,0.0,1.0","content":"YOU'RE INVITED!","sizePx":13,"fontPosition":-1,"fontName":"Inter","alignment":2,"isLower":false,"isBold":false,"isUnderline":false,"isItalic":false,"spacing":0.09600000083446503,"lineHeight":20,"textOpacity":255,"colorShadow":0,"blurShadow":80,"offsetX":10,"offsetY":5,"shadowPosition":0,"borderPosition":0,"colorBorder":0,"sizeBorder":5,"backgroundOpacity":255,"paddingBackgroundX":0,"paddingBackgroundY":0,"roundBackground":0,"curve":0,"gradientPosition":0,"angleGradientText":0,"palettePosition":0,"colorText":-1,"colorPosition":1,"colorBackgroundPosition":0,"colorBackground":0,"gradientBackgroundPosition":0,"angleGradientBackground":90,"colorBorderBackground":0,"colorBorderBackgroundPosition":0,"borderBackgroundOpacity":255,"sizeBorderBackground":3,"isLock":false}],"ext":{"en":["halloween","holiday","illustration","party","celebration","orange","bright orange color","ghost","sunglasses","entertainment","costume","fun","funny","event","invitation"]}}